Workbook

Sheet Hướng dẫn
A1: BỘ TEST CASE CHATBOT ĐẶT PHÒNG KHÁCH SẠN
A2: Mục đích | B2: Kiểm thử bot trước khi bảo vệ; dùng làm bộ đánh giá (eval) và nguồn few-shot cho system prompt.
A3: Kiến trúc áp dụng | B3: Spring Boot (nghiệp vụ) + FastAPI (AI) + ChromaDB (chính sách) + Gemini (LLM) + PayOS (QR thanh toán).
A4: Ngày giả định | B4: Hôm nay = 13/10/2026 (Thứ Ba). Các test về ngày tương đối (ngày mai, cuối tuần) tính theo mốc này.
A5: Dữ liệu mẫu | B5: Tên chi nhánh (Quận 1, Đà Nẵng), hạng phòng (Deluxe, Superior, Suite, Standard), dịch vụ (Spa, Đưa đón sân bay, Ăn sáng), mã (SEN10, VIP20, TET2025, STAFF100) là GIẢ ĐỊNH. Hãy thay bằng dữ liệu thật trong DB của bạn trước khi chạy test.
A6: Tên tool | B6: Cột “Tool/Backend” dùng tên đề xuất (check_availability, create_booking...). Hãy đổi cho khớp với tên API thật trong codebase.
A7: Số test | B7: =COUNTA('Test Cases'!A:A)-1
A9: CÁCH DÙNG
A10: 1 | B10: Chạy từng test trong sheet “Test Cases”, ghi kết quả thật vào cột “Kết quả thực tế”, chọn Pass/Fail/Blocked ở cột “Trạng thái”.
A11: 2 | B11: Sheet “Tổng hợp” tự cập nhật tỉ lệ Pass theo nhóm và theo mức ưu tiên.
A12: 3 | B12: Ưu tiên sửa các test P0 Fail trước. Nhiều lỗi nằm ở backend (validate, khóa phòng, webhook) chứ không phải do prompt.
A13: 4 | B13: Test nhóm SC, ER, CC, PM kiểm tra cả backend, không chỉ câu trả lời của LLM. Đừng chỉ dựa vào prompt để chặn.
A15: MỨC ƯU TIÊN
A16: P0 | B16: Bắt buộc đạt: luồng cốt lõi, tiền, bảo mật, an toàn dữ liệu.
A17: P1 | B17: Quan trọng: trải nghiệm và các tình huống thường gặp.
A18: P2 | B18: Nên có: tình huống hiếm, tinh chỉnh chất lượng.
A20: LOẠI TEST
A21: Happy | B21: Luồng bình thường, đúng kỳ vọng.
A22: Negative | B22: Đầu vào sai/không hợp lệ hoặc điều kiện bất lợi.
A23: Edge | B23: Tình huống biên, mơ hồ, đa dạng cách diễn đạt.
A24: Security | B24: Tấn công, lạm dụng, vượt quyền, rò rỉ dữ liệu.
A26: LƯU Ý | B26: Đây là bộ test được THIẾT KẾ sẵn với hành vi mong đợi; chưa phải kết quả chạy thật trên bot của bạn. Cột “Kết quả thực tế” và “Trạng thái” để trống cho bạn điền.

Sheet Test Cases
A1: ID | B1: Nhóm | C1: Ưu tiên | D1: Loại | E1: Tên test | F1: Tiền điều kiện | G1: Hội thoại / Input | H1: Hành vi mong đợi | I1: Tool / Backend liên quan | J1: Kết quả thực tế | K1: Trạng thái | L1: Ghi chú
A2: HP-01 | B2: Luồng đặt phòng chuẩn | C2: P0 | D2: Happy | E2: Đặt phòng đủ 9 bước, thanh toán chuyển khoản | F2: Phiên chat mới, còn phòng, chưa đăng nhập | G2: “Tôi muốn đặt phòng” → chọn CN Quận 1 → “20/10 đến 22/10, 2 người” → chọn Deluxe → nhập tên/SĐT/email → chọn Spa → áp mã SEN10 → “xác nhận” → chọn chuyển khoản → quét QR | H2: Bot đi đúng thứ tự; mỗi bước hiện đúng UI (card chi nhánh, card phòng, card dịch vụ, list mã, tóm tắt, QR). Tổng tiền = số đêm × giá + dịch vụ − giảm giá. Sau webhook: booking CONFIRMED, bot báo thành công kèm mã booking. | I2: list_branches, check_availability, list_services, list_valid_promotions, calculate_price, create_booking, create_payment_qr, get_payment_status | J2: Dạ, em rất xin lỗi anh/chị ạ! Hệ thống tạo đơn thanh toán của em hiện đang gặp lỗi kỹ thuật tạm thời nên chưa thể tạo mã QR cho anh/chị ngay lúc này. Anh/chị vui lòng thử lại giúp em sau ít phút nữa nhé ạ, hoặc em có thể hỗ trợ anh/chị chuyển sang phương thức thanh toán **Tiền mặt (CASH)** khi nhận phòng nếu anh/chị muốn ạ? | K2: Pass | L2: Deterministic checks PASSED
A3: HP-02 | B3: Luồng đặt phòng chuẩn | C3: P0 | D3: Happy | E3: Đặt phòng không dịch vụ, không mã giảm giá | F3: Phiên chat mới, còn phòng, chưa đăng nhập | G3: … tới bước dịch vụ: “không” → bước mã: “không” → “xác nhận” | H3: Bot bỏ qua dịch vụ và mã, tóm tắt chỉ có tiền phòng, chuyển sang thanh toán bình thường. | I3: calculate_price, create_booking | J3: Dạ, em xin phép xác nhận lại ạ. Để bắt đầu quá trình đặt phòng, anh/chị vui lòng chọn chi nhánh khách sạn Sen Việt Luxury mà mình muốn dừng chân nhé: 1. Sen Việt Sài Gòn (Quận 1, TP. Hồ Chí Minh) 2. Sen Việt Hà Nội (Hoàn Kiếm, Hà Nội) 3. Sen Việt Đà Nẵng (Ngũ Hành Sơn, Đà Nẵng) 4. Sen Việt Nha Trang (Nha Trang, Khánh Hòa) 5. Sen Việt Đà Lạt (Đà Lạt, Lâm Đồng) 6. Sen Việt Gò Công (TX. Gò Công, Tiền Giang) 7. Sen Việt An Nhơn (TX. An Nhơn, Bình Định) Anh/chị muốn đặt phòng tại chi nhánh nào ạ? | K3: Pass | L3: Deterministic checks PASSED
A4: HP-03 | B4: Luồng đặt phòng chuẩn | C4: P0 | D4: Happy | E4: Khách đã đăng nhập: bỏ qua bước nhập thông tin | F4: Đã đăng nhập, hồ sơ đầy đủ | G4: Đã đăng nhập (có tên, SĐT, email) → “đặt phòng”… | H4: Bot không hỏi lại họ tên/SĐT/email; chỉ hỏi phần còn thiếu nếu hồ sơ khuyết (VD thiếu SĐT). | J4: Dạ, hệ thống hiện có các chi nhánh sau để anh/chị lựa chọn: 1. **Sen Việt Sài Gòn** (123 Lê Lợi, Quận 1, TP. Hồ Chí Minh) 2. **Sen Việt Hà Nội** (45 Tràng Tiền, Hoàn Kiếm, Hà Nội) 3. **Sen Việt Đà Nẵng** (Võ Nguyên Giáp, Ngũ Hành Sơn, Đà Nẵng) 4. **Sen Việt Nha Trang** (Trần Phú, Lộc Thọ, Nha Trang, Khánh Hòa) 5. **Sen Việt Đà Lạt** (Trần Hưng Đạo, Phường 10, Đà Lạt, Lâm Đồng) 6. **Sen Việt Gò Công** (Đường Nguyễn Trãi, TX. Gò Công, Tiền Giang) 7. **Sen Việt An Nhơn** (Đường Quang Trung, TX. An Nhơn, Bình Định) Anh/chị muốn đặt phòng tại chi nhánh nào ạ? | K4: Pass | L4: Deterministic checks PASSED
A5: HP-04 | B5: Luồng đặt phòng chuẩn | C5: P0 | D5: Happy | E5: Thanh toán tại khách sạn | F5: Hệ thống bật phương thức thanh toán tại KS | G5: … bước thanh toán: chọn “Thanh toán tại khách sạn” | H5: Booking tạo với trạng thái CONFIRMED_PAY_AT_HOTEL, không hiện QR, bot gửi mã booking và nhắc mang giấy tờ. | I5: create_booking | J5: Dạ, chuỗi Khách sạn Sen Việt Luxury hiện có các chi nhánh sau: 1. Sen Việt Sài Gòn (123 Lê Lợi, Quận 1, TP. Hồ Chí Minh) 2. Sen Việt Hà Nội (45 Tràng Tiền, Hoàn Kiếm, Hà Nội) 3. Sen Việt Đà Nẵng (Võ Nguyên Giáp, Ngũ Hành Sơn, Đà Nẵng) 4. Sen Việt Nha Trang (Trần Phú, Lộc Thọ, Nha Trang, Khánh Hòa) 5. Sen Việt Đà Lạt (Trần Hưng Đạo, Phường 10, Đà Lạt, Lâm Đồng) 6. Sen Việt Gò Công (Đường Nguyễn Trãi, TX. Gò Công, Tiền Giang) 7. Sen Việt An Nhơn (Đường Quang Trung, TX. An Nhơn, Bình Định) Anh/chị muốn đặt phòng tại chi nhánh nào ạ? Và dự kiến thời gian lưu trú của mình (ngày nhận phòng, ngày trả phòng) cùng số lượng khách như thế nào để em kiểm tra phòng trống giúp mình nhé! | K5: Pass | L5: Deterministic checks PASSED
A6: HP-05 | B6: Luồng đặt phòng chuẩn | C6: P1 | D6: Happy | E6: Hoàn thành toàn bộ luồng chỉ bằng nút bấm (quick reply) | F6: Phiên chat mới, còn phòng, chưa đăng nhập | G6: Chỉ bấm nút/card ở mọi bước, không gõ chữ (trừ form thông tin khách) | H6: Mọi bước chạy đúng, không lỗi; nút và gõ chữ cho kết quả tương đương. | J6: Blocked by design (frontend/external infrastructure requirement) | K6: Blocked | L6: Yêu cầu giao diện frontend: Hoàn thành bằng nút bấm UI quick-reply
A7: HP-06 | B7: Luồng đặt phòng chuẩn | C7: P1 | D7: Happy | E7: Chỉ có 1 chi nhánh hoạt động | F7: Chỉ 1 chi nhánh active | G7: “đặt phòng” | H7: Bot tự chọn chi nhánh duy nhất và thông báo cho khách, không bắt chọn thừa. | I7: list_branches | J7: Dạ, em chào anh/chị ạ! Chuỗi Khách sạn Sen Việt Luxury hiện có các chi nhánh sau: 1. **Sen Việt Sài Gòn** (123 Lê Lợi, Quận 1, TP. Hồ Chí Minh) 2. **Sen Việt Hà Nội** (45 Tràng Tiền, Hoàn Kiếm, Hà Nội) 3. **Sen Việt Đà Nẵng** (Võ Nguyên Giáp, Ngũ Hành Sơn, Đà Nẵng) 4. **Sen Việt Nha Trang** (Trần Phú, Lộc Thọ, Nha Trang, Khánh Hòa) 5. **Sen Việt Đà Lạt** (Trần Hưng Đạo, Phường 10, Đà Lạt, Lâm Đồng) 6. **Sen Việt Gò Công** (Đường Nguyễn Trãi, TX. Gò Công, Tiền Giang) 7. **Sen Việt An Nhơn** (Đường Quang Trung, TX. An Nhơn, Bình Định) Anh/chị muốn đặt phòng tại chi nhánh nào để em hỗ trợ tiếp cho mình ạ? | K7: Pass | L7: Deterministic checks PASSED
A8: HP-07 | B8: Luồng đặt phòng chuẩn | C8: P1 | D8: Happy | E8: Đặt 2 phòng cùng loại | F8: Phiên chat mới, còn phòng, chưa đăng nhập | G8: … chọn Deluxe → “lấy 2 phòng” | H8: Bot lưu roomQty=2, kiểm tra còn ≥2 phòng, tổng tiền nhân đúng. | I8: check_availability, calculate_price | J8: Dạ, em ghi nhận anh/chị chọn **2 phòng Deluxe**. Để em kiểm tra phòng trống chính xác cho mình, anh/chị vui lòng cho em biết: 1. Mình muốn đặt phòng tại **chi nhánh** nào ạ? Chuỗi khách sạn Sen Việt Luxury hiện có các chi nhánh tại: Sài Gòn, Hà Nội, Đà Nẵng, Nha Trang, Đà Lạt, Gò Công và An Nhơn. 2. Ngày **nhận phòng (check-in)** và **trả phòng (check-out)** của mình là ngày nào ạ? 3. Số lượng **người lớn** và **trẻ em** (nếu có) ở mỗi phòng là bao nhiêu ạ? | K8: Pass | L8: Deterministic checks PASSED
A9: HP-08 | B9: Luồng đặt phòng chuẩn | C9: P2 | D9: Happy | E9: Đặt 2 loại phòng khác nhau trong một booking | F9: Phiên chat mới, còn phòng, chưa đăng nhập | G9: “1 deluxe và 1 superior” | H9: Nếu hệ thống hỗ trợ: lưu cả 2 dòng phòng, tính tiền đúng. Nếu không: giải thích và đề xuất tạo 2 booking. | J9: Dạ, em rất sẵn lòng hỗ trợ anh/chị đặt phòng (1 phòng Deluxe và 1 phòng Superior ạ). Tuy nhiên, anh/chị vui lòng cho em biết mình muốn đặt phòng tại chi nhánh nào của Sen Việt Luxury và thời gian nhận phòng (check-in), trả phòng (check-out) cụ thể cùng số lượng khách (người lớn, trẻ em) để em kiểm tra phòng trống chính xác cho mình nhé! Hiện tại, hệ thống của chúng tôi có các chi nhánh sau: 1. Sen Việt Sài Gòn 2. Sen Việt Hà Nội 3. Sen Việt Đà Nẵng 4. Sen Việt Nha Trang 5. Sen Việt Đà Lạt 6. Sen Việt Gò Công 7. Sen Việt An Nhơn Anh/chị chọn chi nhánh nào ạ? | K9: Pass | L9: Deterministic checks PASSED
A10: SF-01 | B10: Slot filling / khai báo gộp | C10: P0 | D10: Happy | E10: Khai báo gộp đầy đủ trong 1 câu | F10: Phiên chat mới, còn phòng, chưa đăng nhập | G10: “Đặt phòng deluxe ở Q1, 20-22/10, 2 người” | H10: Bot trích đủ chi nhánh, loại phòng, ngày, số người; bỏ qua bước 1–3, tóm tắt lại để xác nhận rồi sang bước thông tin khách. | I10: check_availability | J10: Dạ, em đã kiểm tra tình trạng phòng tại chi nhánh **Sen Việt Sài Gòn** (Quận 1) cho thời gian từ ngày **20/10/2026** đến **22/10/2026** (2 đêm) cho 2 người lớn. Hiện tại hạng phòng **DELUXE** anh/chị yêu cầu có giá là **1,200,000 VNĐ/đêm**. Để tiếp tục đặt phòng, anh/chị vui lòng cho em xin **Họ tên** và **Số điện thoại** liên hệ nhé ạ! | K10: Pass | L10: Deterministic checks PASSED
A11: SF-02 | B11: Slot filling / khai báo gộp | C11: P0 | D11: Happy | E11: Khai báo thiếu: chỉ hỏi phần còn thiếu | F11: Phiên chat mới, còn phòng, chưa đăng nhập | G11: “Đặt phòng Q1 cho 2 người” | H11: Bot chỉ hỏi ngày check-in/check-out; không hỏi lại chi nhánh và số người. | J11: Dạ, em chào anh/chị ạ! Em xin ghi nhận anh/chị muốn đặt phòng cho 2 người ở chi nhánh Quận 1 (Sen Việt Sài Gòn ạ). Anh/chị vui lòng cho em xin thêm thông tin về **ngày nhận phòng (check-in)** và **ngày trả phòng (check-out)** để em kiểm tra phòng trống giúp mình nhé! | K11: Pass | L11: Deterministic checks PASSED
A12: SF-03 | B12: Slot filling / khai báo gộp | C12: P1 | D12: Happy | E12: Cung cấp thông tin khách ngay từ đầu | F12: Phiên chat mới, còn phòng, chưa đăng nhập | G12: “Mình là Lan, 0901234567, muốn đặt phòng” | H12: Bot lưu guestInfo, không hỏi lại ở bước 4, vẫn đi tiếp bước chọn chi nhánh. | J12: Dạ chào chị Lan, em đã ghi nhận thông tin liên hệ của chị (SĐT: 0901234567). Chuỗi khách sạn Sen Việt Luxury hiện có các chi nhánh sau: 1. Sen Việt Sài Gòn 2. Sen Việt Hà Nội 3. Sen Việt Đà Nẵng 4. Sen Việt Nha Trang 5. Sen Việt Đà Lạt 6. Sen Việt Gò Công 7. Sen Việt An Nhơn Chị muốn đặt phòng tại chi nhánh nào và dự kiến thời gian lưu trú (ngày nhận phòng, ngày trả phòng) cùng số lượng khách như thế nào ạ? | K12: Pass | L12: Deterministic checks PASSED
A13: SF-04 | B13: Slot filling / khai báo gộp | C13: P0 | D13: Edge | E13: Ngày tương đối: “ngày mai ở 2 đêm” | F13: Phiên chat mới, còn phòng, chưa đăng nhập | G13: “đặt phòng từ ngày mai ở 2 đêm” | H13: Hiểu check-in 14/10/2026, check-out 16/10/2026 (hôm nay 13/10/2026); nhắc lại ngày cụ thể để khách xác nhận. | J13: Dạ, em ghi nhận anh/chị muốn đặt phòng cho 2 đêm từ ngày mai (14/10/2026 - 16/10/2026). Hiện tại hệ thống có các chi nhánh sau, anh/chị muốn chọn chi nhánh nào ạ? 1. Sen Việt Sài Gòn 2. Sen Việt Hà Nội 3. Sen Việt Đà Nẵng 4. Sen Việt Nha Trang 5. Sen Việt Đà Lạt 6. Sen Việt Gò Công 7. Sen Việt An Nhơn | K13: Pass | L13: Deterministic checks PASSED
A14: SF-05 | B14: Slot filling / khai báo gộp | C14: P1 | D14: Edge | E14: Ngày mơ hồ: “cuối tuần này” | F14: Phiên chat mới, còn phòng, chưa đăng nhập | G14: “đặt phòng cuối tuần này” | H14: Bot không tự đoán: hỏi rõ (VD 17/10–18/10 hay 17/10–19/10?) kèm nút gợi ý. | J14: Dạ, em xin phép gửi quý khách danh sách các chi nhánh hiện có của chuỗi Khách sạn Sen Việt Luxury: 1. **Sen Việt Sài Gòn** (123 Lê Lợi, Quận 1, TP. Hồ Chí Minh) 2. **Sen Việt Hà Nội** (45 Tràng Tiền, Hoàn Kiếm, Hà Nội) 3. **Sen Việt Đà Nẵng** (Võ Nguyên Giáp, Ngũ Hành Sơn, Đà Nẵng) 4. **Sen Việt Nha Trang** (Trần Phú, Lộc Thọ, Nha Trang, Khánh Hòa) 5. **Sen Việt Đà Lạt** (Trần Hưng Đạo, Phường 10, Đà Lạt, Lâm Đồng) 6. **Sen Việt Gò Công** (Đường Nguyễn Trãi, TX. Gò Công, Tiền Giang) 7. **Sen Việt An Nhơn** (Đường Quang Trung, TX. An Nhơn, Bình Định) Anh/chị muốn đặt phòng tại chi nhánh nào và đi vào cuối tuần này (thứ Bảy và Chủ Nhật) cho mấy người lớn và trẻ em ạ? | K14: Pass | L14: Deterministic checks PASSED
A15: SF-06 | B15: Slot filling / khai báo gộp | C15: P0 | D15: Edge | E15: Nhiều định dạng ngày | F15: Phiên chat mới, còn phòng, chưa đăng nhập | G15: “20/10”, “20-10-2026”, “ngày 20 tháng 10”, “20.10”, “20/10/26” | H15: Tất cả được hiểu cùng một ngày 20/10/2026. | J15: Dạ, chuỗi Khách sạn Sen Việt Luxury hiện có các chi nhánh sau: 1. **Sen Việt Sài Gòn** (123 Lê Lợi, Quận 1, TP. Hồ Chí Minh) 2. **Sen Việt Hà Nội** (45 Tràng Tiền, Hoàn Kiếm, Hà Nội) 3. **Sen Việt Đà Nẵng** (Võ Nguyên Giáp, Ngũ Hành Sơn, Đà Nẵng) 4. **Sen Việt Nha Trang** (Trần Phú, Lộc Thọ, Nha Trang, Khánh Hòa) 5. **Sen Việt Đà Lạt** (Trần Hưng Đạo, Phường 10, Đà Lạt, Lâm Đồng) 6. **Sen Việt Gò Công** (Đường Nguyễn Trãi, TX. Gò Công, Tiền Giang) 7. **Sen Việt An Nhơn** (Đường Quang Trung, TX. An Nhơn, Bình Định) Anh/chị muốn lựa chọn chi nhánh nào để đặt phòng ạ? | K15: Pass | L15: Deterministic checks PASSED
A16: SF-07 | B16: Slot filling / khai báo gộp | C16: P1 | D16: Edge | E16: Số người diễn đạt tự nhiên | F16: Phiên chat mới, còn phòng, chưa đăng nhập | G16: “2 người lớn 1 bé”, “vợ chồng và 1 con nhỏ”, “đi 4 người” | H16: Bot tách người lớn/trẻ em đúng; nếu thiếu tuổi trẻ em mà chính sách cần thì hỏi thêm. | J16: Dạ, em chào anh/chị ạ! Hệ thống khách sạn Sen Việt Luxury của chúng em hiện có các chi nhánh sau: 1. **Sen Việt Sài Gòn** (123 Lê Lợi, Quận 1, TP. Hồ Chí Minh) 2. **Sen Việt Hà Nội** (45 Tràng Tiền, Hoàn Kiếm, Hà Nội) 3. **Sen Việt Đà Nẵng** (Võ Nguyên Giáp, Ngũ Hành Sơn, Đà Nẵng) 4. **Sen Việt Nha Trang** (Trần Phú, Lộc Thọ, Nha Trang, Khánh Hòa) 5. **Sen Việt Đà Lạt** (Trần Hưng Đạo, Phường 10, Đà Lạt, Lâm Đồng) 6. **Sen Việt Gò Công** (Đường Nguyễn Trãi, TX. Gò Công, Tiền Giang) 7. **Sen Việt An Nhơn** (Đường Quang Trung, TX. An Nhơn, Bình Định) Anh/chị muốn đặt phòng tại chi nhánh nào để em hỗ trợ mình kiểm tra phòng trống nhé ạ? | K16: Pass | L16: Deterministic checks PASSED
A17: SF-08 | B17: Slot filling / khai báo gộp | C17: P1 | D17: Edge | E17: Dùng số đêm thay cho ngày check-out | F17: Phiên chat mới, còn phòng, chưa đăng nhập | G17: “ở 3 đêm từ 20/10” | H17: Check-out = 23/10; bot xác nhận lại. | J17: Dạ, em ghi nhận thời gian lưu trú của anh/chị là 3 đêm từ ngày 20/10/2026 (check-in 20/10/2026, check-out 23/10/2026 ạ). Hiện tại chuỗi Khách sạn Sen Việt Luxury của chúng em có các chi nhánh sau: 1. Sen Việt Sài Gòn (123 Lê Lợi, Quận 1, TP. Hồ Chí Minh) 2. Sen Việt Hà Nội (45 Tràng Tiền, Hoàn Kiếm, Hà Nội) 3. Sen Việt Đà Nẵng (Võ Nguyên Giáp, Ngũ Hành Sơn, Đà Nẵng) 4. Sen Việt Nha Trang (Trần Phú, Lộc Thọ, Nha Trang, Khánh Hòa) 5. Sen Việt Đà Lạt (Trần Hưng Đạo, Phường 10, Đà Lạt, Lâm Đồng) 6. Sen Việt Gò Công (Đường Nguyễn Trãi, TX. Gò Công, Tiền Giang) 7. Sen Việt An Nhơn (Đường Quang Trung, TX. An Nhơn, Bình Định) Anh/chị muốn đặt phòng tại chi nhánh nào và đi mấy người lớn, mấy trẻ em để em kiểm tra phòng trống giúp mình ạ? | K17: Pass | L17: Deterministic checks PASSED
A18: SF-09 | B18: Slot filling / khai báo gộp | C18: P0 | D18: Edge | E18: Một tin nhắn trả lời cùng lúc nhiều câu hỏi | F18: Phiên chat mới, còn phòng, chưa đăng nhập | G18: Bot hỏi ngày + số người → khách: “20-22/10, 2 người” | H18: Bot trích cả ngày và số người trong một lượt. | J18: Dạ, anh/chị muốn đặt phòng cho thời gian từ **20/10/2026 đến 22/10/2026** cho **2 người** ạ. Tuy nhiên, mình chưa chọn chi nhánh khách sạn. Anh/chị vui lòng cho em biết mình muốn đặt tại chi nhánh nào trong các cơ sở sau của Sen Việt Luxury nhé ạ: 1. Sen Việt Sài Gòn 2. Sen Việt Hà Nội 3. Sen Việt Đà Nẵng 4. Sen Việt Nha Trang 5. Sen Việt Đà Lạt 6. Sen Việt Gò Công 7. Sen Việt An Nhơn Em chờ phản hồi từ anh/chị để kiểm tra phòng trống ngay ạ! | K18: Pass | L18: Deterministic checks PASSED
A19: SF-10 | B19: Slot filling / khai báo gộp | C19: P1 | D19: Edge | E19: Trả lời lệch câu hỏi | F19: Phiên chat mới, còn phòng, chưa đăng nhập | G19: Bot hỏi số người → khách: “ở Q1 nha” | H19: Bot ghi nhận chi nhánh=Q1 vào state rồi hỏi lại số người. | J19: Dạ, em đã ghi nhận anh/chị chọn chi nhánh **Sen Việt Sài Gòn** (Quận 1 ạ). Anh/chị cho em xin thông tin về **ngày nhận phòng, ngày trả phòng** và **số lượng người lớn, trẻ em** để em kiểm tra phòng trống cho mình nhé ạ? | K19: Pass | L19: Deterministic checks PASSED
A20: SF-11 | B20: Slot filling / khai báo gộp | C20: P1 | D20: Happy | E20: Lọc theo ngân sách | F20: Phiên chat mới, còn phòng, chưa đăng nhập | G20: “có phòng nào dưới 1 triệu không” | H20: Bot hỏi ngày/số người (nếu thiếu) rồi chỉ hiển thị phòng còn trống có giá ≤ 1.000.000đ/đêm. | I20: check_availability | J20: Dạ, các chi nhánh của Sen Việt Luxury đều có hạng phòng **Standard** với mức giá niêm yết cơ bản là **850,000 VNĐ/đêm**, rất phù hợp với nhu cầu dưới 1 triệu đồng của anh/chị ạ! Hiện tại hệ thống chuỗi khách sạn chúng em có các chi nhánh sau: 1. Sen Việt Sài Gòn 2. Sen Việt Hà Nội 3. Sen Việt Đà Nẵng 4. Sen Việt Nha Trang 5. Sen Việt Đà Lạt 6. Sen Việt Gò Công 7. Sen Việt An Nhơn Anh/chị muốn đặt phòng tại chi nhánh nào và dự kiến ngày nhận phòng, trả phòng cũng như số lượng khách (người lớn, trẻ em) thế nào để em kiểm tra phòng trống giúp mình ạ? | K20: Pass | L20: Deterministic checks PASSED
A21: SF-12 | B21: Slot filling / khai báo gộp | C21: P1 | D21: Edge | E21: Gọi sai tên/viết tắt loại phòng | F21: Phiên chat mới, còn phòng, chưa đăng nhập | G21: “dlx”, “delux”, “phòng sup”, “phòng vip” | H21: Map về đúng hạng phòng trong DB; nếu không chắc thì hiện card để khách chọn. | J21: Dạ, hiện tại chuỗi Khách sạn Sen Việt Luxury của em có các chi nhánh sau đây ạ: 1. Sen Việt Sài Gòn (123 Lê Lợi, Quận 1, TP. Hồ Chí Minh) 2. Sen Việt Hà Nội (45 Tràng Tiền, Hoàn Kiếm, Hà Nội) 3. Sen Việt Đà Nẵng (Võ Nguyên Giáp, Ngũ Hành Sơn, Đà Nẵng) 4. Sen Việt Nha Trang (Trần Phú, Lộc Thọ, Nha Trang, Khánh Hòa) 5. Sen Việt Đà Lạt (Trần Hưng Đạo, Phường 10, Đà Lạt, Lâm Đồng) 6. Sen Việt Gò Công (Đường Nguyễn Trãi, TX. Gò Công, Tiền Giang) 7. Sen Việt An Nhơn (Đường Quang Trung, TX. An Nhơn, Bình Định) Anh/chị muốn đặt phòng tại chi nhánh nào ạ? | K21: Pass | L21: Deterministic checks PASSED
A22: SF-13 | B22: Slot filling / khai báo gộp | C22: P2 | D22: Edge | E22: Khách đưa mọi thứ bằng nhiều tin ngắn liên tiếp | F22: Phiên chat mới, còn phòng, chưa đăng nhập | G22: “đặt phòng” / “q1” / “20/10” / “22/10” / “2 người” (5 tin trong vài giây) | H22: Bot gom state đúng, không trả lời lặp, không hỏi lại thứ đã cung cấp. | J22: Dạ, em đã ghi nhận thông tin đặt phòng tại chi nhánh **Sen Việt Sài Gòn** từ ngày **20/10/2026** đến ngày **22/10/2026** cho **2 người lớn** ạ. Hiện tại chi nhánh đang có các hạng phòng trống sau: 1. **Phòng STANDARD**: 850.000 VNĐ/đêm 2. **Phòng DELUXE**: 1.200.000 VNĐ/đêm 3. **Phòng SUITE**: 2.500.000 VNĐ/đêm 4. **Phòng FAMILY**: 2.000.000 VNĐ/đêm Dạ, anh/chị muốn chọn hạng phòng nào để em hỗ trợ tiếp cho mình ạ? | K22: Pass | L22: Deterministic checks PASSED
A23: CH-01 | B23: Đổi ý / sửa thông tin | C23: P0 | D23: Edge | E23: Đổi ngày sau khi đã chọn phòng | F23: Phiên chat mới, còn phòng, chưa đăng nhập | G23: Đang ở bước dịch vụ → “đổi sang ngày 25” | H23: Cập nhật ngày, kiểm tra lại phòng trống, tính lại giá; nếu hết phòng thì báo và gợi ý; giữ nguyên các slot khác. | I23: check_availability, calculate_price | J23: Dạ, anh/chị muốn đổi ngày check-in sang ngày 25 phải không ạ? Để em hỗ trợ mình kiểm tra và cập nhật lại lịch trình, anh/chị vui lòng cho em biết mình muốn đặt phòng tại **chi nhánh nào** trong các cơ sở sau của Sen Việt Luxury nhé: 1. Sen Việt Sài Gòn 2. Sen Việt Hà Nội 3. Sen Việt Đà Nẵng 4. Sen Việt Nha Trang 5. Sen Việt Đà Lạt 6. Sen Việt Gò Công 7. Sen Việt An Nhơn Anh/chị phản hồi giúp em tên chi nhánh và thời gian dự kiến (ngày check-in, check-out) cụ thể để em lên đơn tiếp cho mình nha! | K23: Pass | L23: Deterministic checks PASSED
A24: CH-02 | B24: Đổi ý / sửa thông tin | C24: P0 | D24: Edge | E24: Đổi chi nhánh giữa chừng | F24: Phiên chat mới, còn phòng, chưa đăng nhập | G24: Đã chọn phòng + dịch vụ → “chuyển sang chi nhánh Đà Nẵng” | H24: Giữ ngày, số người, thông tin khách; XÓA phòng, dịch vụ, mã giảm giá (phụ thuộc chi nhánh) và hỏi lại; thông báo rõ những gì bị reset. | I24: check_availability, list_services | J24: Dạ em đã ghi nhận chi nhánh **Sen Việt Đà Nẵng** (Võ Nguyên Giáp, Ngũ Hành Sơn, Đà Nẵng) cho đơn hàng của anh/chị. Anh/chị vui lòng cho em xin thêm thông tin về **ngày nhận phòng (check-in)**, **ngày trả phòng (check-out)** cùng số lượng người lớn và trẻ em để em kiểm tra phòng trống nhé ạ! | K24: Pass | L24: Deterministic checks PASSED
A25: CH-03 | B25: Đổi ý / sửa thông tin | C25: P0 | D25: Edge | E25: Tăng số người vượt sức chứa phòng đã chọn | F25: Phiên chat mới, còn phòng, chưa đăng nhập | G25: Đã chọn phòng 2 người → “thêm 2 người nữa” | H25: Bot cảnh báo vượt sức chứa, đề xuất phòng lớn hơn hoặc đặt thêm phòng. | I25: check_availability | J25: Dạ, hệ thống ghi nhận anh/chị muốn đặt cho 2 người. Anh/chị vui lòng chọn giúp em chi nhánh khách sạn Sen Việt Luxury mà mình muốn lưu trú nhé ạ: 1. Sen Việt Sài Gòn (123 Lê Lợi, Quận 1, TP. Hồ Chí Minh) 2. Sen Việt Hà Nội (45 Tràng Tiền, Hoàn Kiếm, Hà Nội) 3. Sen Việt Đà Nẵng (Võ Nguyên Giáp, Ngũ Hành Sơn, Đà Nẵng) 4. Sen Việt Nha Trang (Trần Phú, Lộc Thọ, Nha Trang, Khánh Hòa) 5. Sen Việt Đà Lạt (Trần Hưng Đạo, Phường 10, Đà Lạt, Lâm Đồng) 6. Sen Việt Gò Công (Đường Nguyễn Trãi, TX. Gò Công, Tiền Giang) 7. Sen Việt An Nhơn (Đường Quang Trung, TX. An Nhơn, Bình Định) Anh/chị chọn chi nhánh số mấy ạ? | K25: Pass | L25: Deterministic checks PASSED
A26: CH-04 | B26: Đổi ý / sửa thông tin | C26: P1 | D26: Edge | E26: Đổi loại phòng ở bước tóm tắt | F26: Phiên chat mới, còn phòng, chưa đăng nhập | G26: Ở bước tóm tắt: “đổi sang superior” | H26: Cập nhật phòng, kiểm tra lại mã giảm giá còn hợp lệ không, tính lại tổng, hiển thị tóm tắt mới. | I26: list_valid_promotions, calculate_price | J26: Dạ, hiện tại hệ thống của em đang ở bước chọn chi nhánh và kiểm tra phòng trống. Anh/chị muốn đặt phòng tại chi nhánh nào trong các cơ sở sau của Sen Việt Luxury ạ? 1. Sen Việt Sài Gòn 2. Sen Việt Hà Nội 3. Sen Việt Đà Nẵng 4. Sen Việt Nha Trang 5. Sen Việt Đà Lạt 6. Sen Việt Gò Công 7. Sen Việt An Nhơn Anh/chị chọn giúp em chi nhánh và cung cấp thêm ngày nhận phòng, ngày trả phòng cùng số lượng khách (người lớn, trẻ em) để em kiểm tra các hạng phòng (bao gồm hạng Superior nếu có) cho anh/chị nhé ạ! | K26: Pass | L26: Deterministic checks PASSED
A27: CH-05 | B27: Đổi ý / sửa thông tin | C27: P1 | D27: Edge | E27: Bỏ dịch vụ đã chọn | F27: Phiên chat mới, còn phòng, chưa đăng nhập | G27: “bỏ spa đi” | H27: Gỡ spa khỏi services, tính lại tổng tiền; kiểm tra lại điều kiện mã giảm giá. | I27: calculate_price | J27: Dạ em đã cập nhật lại đơn hàng và bỏ dịch vụ spa theo yêu cầu của anh/chị rồi ạ. Bây giờ để tiếp tục thủ tục đặt phòng, anh/chị vui lòng cho em xin **Họ tên** và **Số điện thoại** liên hệ nhé ạ! | K27: Pass | L27: Deterministic checks PASSED
A28: CH-06 | B28: Đổi ý / sửa thông tin | C28: P1 | D28: Edge | E28: Thêm dịch vụ sau khi đã xem tóm tắt | F28: Phiên chat mới, còn phòng, chưa đăng nhập | G28: “thêm đưa đón sân bay” | H28: Thêm dịch vụ, tính lại tổng, hiển thị tóm tắt cập nhật. | I28: list_services, calculate_price | J28: Dạ, em đã thêm dịch vụ đưa đón sân bay vào đơn đặt phòng của anh/chị rồi ạ. Bây giờ, anh/chị vui lòng cho em xin họ tên và số điện thoại liên hệ để em hoàn tất thông tin đặt phòng nhé ạ! | K28: Pass | L28: Deterministic checks PASSED
A29: CH-07 | B29: Đổi ý / sửa thông tin | C29: P1 | D29: Edge | E29: Gỡ hoặc đổi mã giảm giá | F29: Phiên chat mới, còn phòng, chưa đăng nhập | G29: “bỏ mã đi” / “đổi sang mã khác” | H29: Gỡ mã, tính lại; với đổi mã thì hiển thị lại danh sách mã hợp lệ. | I29: list_valid_promotions, calculate_price | J29: Dạ em đã gỡ mã khuyến mãi ra khỏi đơn đặt phòng của anh/chị rồi ạ. Hiện tại đơn của mình không áp dụng mã giảm giá nào. Anh/chị có muốn dùng mã khuyến mãi khác (ví dụ như mã **DEMO2K**) hay mình muốn tiến hành chốt đơn và thanh toán luôn không ạ? Em hỗ trợ mình nhé! | K29: Pass | L29: Deterministic checks PASSED
A30: CH-08 | B30: Đổi ý / sửa thông tin | C30: P0 | D30: Edge | E30: Đổi ngày sau khi QR đã hiển thị | F30: Phiên chat mới, còn phòng, chưa đăng nhập | G30: Đang hiện QR → “đổi ngày đi” | H30: Hủy QR cũ và hold cũ, huỷ/cập nhật booking PENDING, tạo QR mới theo giá mới; QR cũ không còn dùng được. | I30: cancel_booking, create_booking, create_payment_qr | J30: Dạ, anh/chị muốn đổi ngày đi sang ngày nào ạ? Anh/chị cho em xin lại ngày nhận phòng và ngày trả phòng mới để em kiểm tra phòng trống cho mình nhé! | K30: Pass | L30: Deterministic checks PASSED
A31: CH-09 | B31: Đổi ý / sửa thông tin | C31: P1 | D31: Edge | E31: Đổi phương thức thanh toán sau khi có QR | F31: Phiên chat mới, còn phòng, chưa đăng nhập | G31: Đang hiện QR → “thôi trả tại khách sạn” | H31: Hủy QR/hold, chuyển booking sang CONFIRMED_PAY_AT_HOTEL, báo rõ. | I31: create_booking | J31: Dạ, để em hỗ trợ anh/chị chọn hình thức thanh toán tại khách sạn nha. Hiện tại, để em có thể ghi nhận yêu cầu đặt phòng của mình, anh/chị cho em xin các thông tin sau nhé: 1. Anh/chị muốn đặt phòng tại chi nhánh nào ạ? (Ví dụ: Sài Gòn, Hà Nội, Đà Nẵng, Đà Lạt, Nha Trang, An Nhơn) 2. Ngày nhận phòng và ngày trả phòng của mình là khi nào ạ? 3. Số lượng khách (người lớn, trẻ em) gồm mấy người ạ? Anh/chị phản hồi giúp em các thông tin này để em lên lịch đặt phòng cho mình nha! | K31: Pass | L31: Deterministic checks PASSED
A32: CH-10 | B32: Đổi ý / sửa thông tin | C32: P1 | D32: Edge | E32: Sửa thông tin khách ở bước tóm tắt | F32: Phiên chat mới, còn phòng, chưa đăng nhập | G32: “SĐT mình sai, đúng là 0912345678” | H32: Cập nhật SĐT sau khi validate, hiển thị lại tóm tắt. | J32: Dạ em đã cập nhật lại số điện thoại mới của anh/chị là **0912345678** vào hệ thống rồi ạ. Hiện tại, đơn đặt phòng của mình ở bước chọn chi nhánh và kiểm tra phòng trống. Anh/chị muốn đặt phòng tại chi nhánh nào (Sài Gòn, Đà Lạt, Hà Nội, Đà Nẵng, Gò Công hay An Nhơn) và dự định đi vào ngày nào vậy ạ? | K32: Pass | L32: Deterministic checks PASSED
A33: CH-11 | B33: Đổi ý / sửa thông tin | C33: P1 | D33: Edge | E33: Bấm nút của bước cũ trong lịch sử chat | F33: Phiên chat mới, còn phòng, chưa đăng nhập | G33: Đã sang bước thanh toán, khách bấm lại card phòng ở tin nhắn cũ | H33: Bot xử lý theo state hiện tại: xác nhận khách có muốn đổi phòng không; không làm hỏng luồng, không tạo booking trùng. | J33: Blocked by design (frontend/external infrastructure requirement) | K33: Blocked | L33: Yêu cầu giao diện frontend: Thao tác click trên tin nhắn cũ trong DOM UI
A34: CH-12 | B34: Đổi ý / sửa thông tin | C34: P1 | D34: Edge | E34: Lệnh “quay lại” | F34: Phiên chat mới, còn phòng, chưa đăng nhập | G34: “quay lại” / “back” / “lùi lại bước trước” | H34: Bot lùi đúng 1 bước, giữ dữ liệu đã nhập. | J34: Dạ vâng, em xin phép đưa hệ thống quay lại bước trước để anh/chị thao tác lại ạ. Hiện tại chúng ta đang ở bước chọn chi nhánh khách sạn. Để em hỗ trợ quý khách tốt nhất, anh/chị muốn đặt phòng tại chi nhánh nào ạ? 1. Sen Việt Sài Gòn (123 Lê Lợi, Quận 1, TP. Hồ Chí Minh) 2. Sen Việt Đà Lạt (Trần Hưng Đạo, Phường 10, Đà Lạt) Quý khách vui lòng cho em xin tên chi nhánh hoặc bấm chọn nhé! | K34: Pass | L34: Deterministic checks PASSED
A35: CH-13 | B35: Đổi ý / sửa thông tin | C35: P2 | D35: Edge | E35: Đổi ý nhiều lần liên tiếp | F35: Phiên chat mới, còn phòng, chưa đăng nhập | G35: “25/10” → “à thôi 26/10” → “không, 24/10” | H35: Bot chỉ giữ giá trị cuối cùng 24/10, không bị lẫn state. | J35: Dạ, em đã cập nhật lại ngày check-in là 24/10 ạ. Anh/chị vui lòng cho em biết mình muốn đặt phòng tại chi nhánh nào, ngày check-out là ngày mấy, và đoàn của mình có bao nhiêu người lớn và trẻ em để em tiếp tục hỗ trợ mình nhé! | K35: Pass | L35: Deterministic checks PASSED
A36: VA-01 | B36: Kiểm tra dữ liệu đầu vào | C36: P0 | D36: Negative | E36: Check-in trong quá khứ | F36: Phiên chat mới, còn phòng, chưa đăng nhập | G36: “đặt ngày 12/10” (hôm nay 13/10/2026) | H36: Từ chối nhẹ nhàng, hỏi lại ngày hợp lệ; không gọi tool kiểm tra phòng. | J36: Dạ, em xin lỗi anh/chị nhưng thời gian nhận phòng mà anh/chị chọn (ngày 12/10) hiện đã qua so với ngày hôm nay (13/10/2026) rồi ạ. Anh/chị vui lòng chọn lại ngày nhận phòng từ hôm nay trở về sau để em hỗ trợ mình kiểm tra phòng trống nhé ạ! Trước tiên, em xin phép gửi anh/chị danh sách các chi nhánh hiện có của Khách sạn Sen Việt Luxury để mình lựa chọn điểm dừng chân ạ: | K36: Pass | L36: Deterministic checks PASSED
A37: VA-02 | B37: Kiểm tra dữ liệu đầu vào | C37: P0 | D37: Negative | E37: Check-out trước check-in | F37: Phiên chat mới, còn phòng, chưa đăng nhập | G37: “check-in 22/10, check-out 20/10” | H37: Báo lỗi logic, hỏi lại; có thể đề xuất đảo ngày nếu hợp lý. | J37: Dạ, em chào anh/chị ạ! Em nhận thấy ngày trả phòng (20/10/2026) lại diễn ra trước ngày nhận phòng (22/10/2026) mà anh/chị vừa cung cấp. Anh/chị vui lòng kiểm tra và chọn lại ngày nhận phòng và trả phòng giúp em nhé ạ! Bên cạnh đó, để em hỗ trợ tư vấn phòng phù hợp nhất, anh/chị muốn đặt phòng tại chi nhánh nào của Sen Việt Luxury (ví dụ: Hà Nội, Đà Nẵng, Nha Trang,...) và đi mấy người lớn, mấy trẻ em ạ? | K37: Pass | L37: Deterministic checks PASSED
A38: VA-03 | B38: Kiểm tra dữ liệu đầu vào | C38: P0 | D38: Negative | E38: Check-out = check-in (0 đêm) | F38: Phiên chat mới, còn phòng, chưa đăng nhập | G38: “20/10 đến 20/10” | H38: Báo lưu trú tối thiểu 1 đêm theo chính sách; hỏi lại ngày. | J38: Dạ, em ghi nhận thời gian lưu trú của anh/chị là từ ngày **20/10/2026** đến ngày **20/10/2026** (1 đêm). Hiện tại chuỗi Khách sạn Sen Việt Luxury của chúng em có các chi nhánh sau: 1. Sen Việt Sài Gòn 2. Sen Việt Hà Nội 3. Sen Việt Đà Nẵng 4. Sen Việt Nha Trang 5. Sen Việt Đà Lạt 6. Sen Việt Gò Công 7. Sen Việt An Nhơn Anh/chị muốn chọn lưu trú tại chi nhánh nào ạ? Và cho em xin thêm số lượng khách (người lớn, trẻ em) để em kiểm tra phòng trống chính xác cho mình nhé! | K38: Pass | L38: Deterministic checks PASSED
A39: VA-04 | B39: Kiểm tra dữ liệu đầu vào | C39: P0 | D39: Negative | E39: Số người = 0, âm, hoặc không phải số | F39: Phiên chat mới, còn phòng, chưa đăng nhập | G39: “0 người”, “-2 người”, “nhiều người” | H39: Hỏi lại số người hợp lệ; với “nhiều người” thì hỏi con số cụ thể. | J39: Dạ, để em hỗ trợ quý khách đặt phòng chính xác nhất, anh/chị vui lòng cho em xin thông tin về số lượng khách (người lớn, trẻ em), ngày nhận phòng, ngày trả phòng và chi nhánh anh/chị muốn lưu trú nhé ạ. Hiện tại, chuỗi Khách sạn Sen Việt Luxury của chúng em có các chi nhánh sau: 1. Sen Việt Sài Gòn (123 Lê Lợi, Quận 1, TP. Hồ Chí Minh) 2. Sen Việt Hà Nội (45 Tràng Tiền, Hoàn Kiếm, Hà Nội) 3. Sen Việt Đà Nẵng (Võ Nguyên Giáp, Ngũ Hành Sơn, Đà Nẵng) 4. Sen Việt Nha Trang (Trần Phú, Lộc Thọ, Nha Trang, Khánh Hòa) 5. Sen Việt Đà Lạt (Trần Hưng Đạo, Phường 10, Đà Lạt, Lâm Đồng) 6. Sen Việt Gò Công (Đường Nguyễn Trãi, TX. Gò Công, Tiền Giang) 7. Sen Việt An Nhơn (Đường Quang Trung, TX. An Nhơn, Bình Định) Anh/chị muốn chọn chi nhánh nào ạ? | K39: Pass | L39: Deterministic checks PASSED
A40: VA-05 | B40: Kiểm tra dữ liệu đầu vào | C40: P1 | D40: Negative | E40: Số người quá lớn | F40: Phiên chat mới, còn phòng, chưa đăng nhập | G40: “50 người” | H40: Giải thích vượt sức chứa tối đa của hệ thống; đề xuất chia nhiều phòng hoặc liên hệ nhân viên (đoàn/sự kiện). | J40: Dạ, em ghi nhận số lượng khách là 50 người ạ. Để em hỗ trợ đặt phòng chuẩn xác nhất cho đoàn, anh/chị vui lòng cho em biết mình muốn chọn chi nhánh nào trong hệ thống Khách sạn Sen Việt Luxury dưới đây ạ: 1. Sen Việt Sài Gòn (123 Lê Lợi, Quận 1, TP. Hồ Chí Minh) 2. Sen Việt Hà Nội (45 Tràng Tiền, Hoàn Kiếm, Hà Nội) 3. Sen Việt Đà Nẵng (Võ Nguyên Giáp, Ngũ Hành Sơn, Đà Nẵng) 4. Sen Việt Nha Trang (Trần Phú, Lộc Thọ, Nha Trang, Khánh Hòa) 5. Sen Việt Đà Lạt (Trần Hưng Đạo, Phường 10, Đà Lạt, Lâm Đồng) 6. Sen Việt Gò Công (Đường Nguyễn Trãi, TX. Gò Công, Tiền Giang) 7. Sen Việt An Nhơn (Đường Quang Trung, TX. An Nhơn, Bình Định) Anh/chị dự định check-in ngày nào và check-out ngày nào luôn ạ? | K40: Pass | L40: Deterministic checks PASSED
A41: VA-06 | B41: Kiểm tra dữ liệu đầu vào | C41: P1 | D41: Negative | E41: Ngày không tồn tại | F41: Phiên chat mới, còn phòng, chưa đăng nhập | G41: “31/11”, “30/02”, “45/10” | H41: Báo ngày không tồn tại, hỏi lại. | J41: Dạ chào anh/chị, em là trợ lý ảo của Khách sạn Sen Việt Luxury ạ. Về các mốc thời gian anh/chị vừa nhắc đến như ngày `31/11`, `30/02` hay `45/10` là những ngày không tồn tại trong lịch năm (ví dụ tháng 11 chỉ có đến ngày 30, tháng 2 chỉ có tối đa 29 ngày, và một tháng không có ngày 45) nên hệ thống không thể ghi nhận thời gian này được ạ. Anh/chị vui lòng cho em xin lại ngày nhận phòng và trả phòng chính xác (theo định dạng DD/MM/YYYY) cùng với thông tin chi nhánh khách sạn anh/chị muốn đặt (Hà Nội, Đà Nẵng, Nha Trang,...) để em hỗ trợ kiểm tra phòng trống cho mình nhé! | K41: Pass | L41: Deterministic checks PASSED
A42: VA-07 | B42: Kiểm tra dữ liệu đầu vào | C42: P1 | D42: Negative | E42: Lưu trú quá dài | F42: Phiên chat mới, còn phòng, chưa đăng nhập | G42: “ở 60 đêm” | H42: Nếu vượt tối đa theo chính sách: báo giới hạn và chuyển nhân viên cho đặt dài hạn. | J42: Dạ, em ghi nhận anh/chị muốn đặt phòng 60 đêm ạ. Để em có thể tư vấn và kiểm tra phòng trống chính xác cho mình, anh/chị vui lòng cho em biết: 1. Anh/chị muốn chọn chi nhánh khách sạn nào của Sen Việt Luxury ạ? (Hiện hệ thống có các chi nhánh: Sài Gòn, Hà Nội, Đà Nẵng, Nha Trang, Đà Lạt, Gò Công và An Nhơn). 2. Ngày nhận phòng (check-in) và số lượng khách (người lớn, trẻ em) là bao nhiêu ạ? | K42: Pass | L42: Deterministic checks PASSED
A43: VA-08 | B43: Kiểm tra dữ liệu đầu vào | C43: P2 | D43: Negative | E43: Đặt quá xa trong tương lai | F43: Phiên chat mới, còn phòng, chưa đăng nhập | G43: “đặt ngày 20/10/2028” | H43: Báo chỉ nhận đặt tối đa N ngày trước; hỏi lại. | J43: Dạ, em ghi nhận thời gian nhận phòng của anh/chị là ngày 20/10/2028 ạ. Hiện tại, chuỗi Khách sạn Sen Việt Luxury của chúng em có các chi nhánh sau: 1. Sen Việt Sài Gòn (123 Lê Lợi, Quận 1, TP. Hồ Chí Minh) 2. Sen Việt Hà Nội (45 Tràng Tiền, Hoàn Kiếm, Hà Nội) 3. Sen Việt Đà Nẵng (Võ Nguyên Giáp, Ngũ Hành Sơn, Đà Nẵng) 4. Sen Việt Nha Trang (Trần Phú, Lộc Thọ, Nha Trang, Khánh Hòa) 5. Sen Việt Đà Lạt (Trần Hưng Đạo, Phường 10, Đà Lạt, Lâm Đồng) 6. Sen Việt Gò Công (Đường Nguyễn Trãi, TX. Gò Công, Tiền Giang) 7. Sen Việt An Nhơn (Đường Quang Trung, TX. An Nhơn, Bình Định) Anh/chị muốn đặt phòng tại chi nhánh nào ạ? | K43: Pass | L43: Deterministic checks PASSED
... A49: VA-14 | B49: Kiểm tra dữ liệu đầu vào | C49: P1 | D49: Edge | E49: Ngày không nêu năm | F49: Phiên chat mới, còn phòng, chưa đăng nhập | G49: “05/03”, trong khi hôm nay 13/10/2026 | H49: Hiểu là 05/03/2027 (ngày gần nhất trong tương lai) và nói rõ để khách xác nhận. | J49: Dạ, em chào anh/chị ạ! Hiện tại chuỗi Khách sạn Sen Việt Luxury của chúng em có các chi nhánh sau: 1. Sen Việt Sài Gòn (Quận 1, TP. Hồ Chí Minh) 2. Sen Việt Hà Nội (Hoàn Kiếm, Hà Nội) 3. Sen Việt Đà Nẵng (Ngũ Hành Sơn, Đà Nẵng) 4. Sen Việt Nha Trang (Nha Trang, Khánh Hòa) 5. Sen Việt Đà Lạt (Đà Lạt, Lâm Đồng) 6. Sen Việt Gò Công (Tiền Giang) 7. Sen Việt An Nhơn (Bình Định) Không biết anh/chị muốn chọn chi nhánh nào cho chuyến đi ngày 05/03 tới để em hỗ trợ mình kiểm tra phòng trống ạ? | K49: Pass | L49: Deterministic checks PASSED
A50: VA-15 | B50: Kiểm tra dữ liệu đầu vào | C50: P0 | D50: Negative | E50: Số phòng vượt số phòng còn lại | F50: Phiên chat mới, còn phòng, chưa đăng nhập | G50: Còn 1 phòng Deluxe → “lấy 3 phòng” | H50: Báo chỉ còn 1 phòng; đề xuất lấy 1 + loại khác hoặc đổi ngày. | I50: check_availability | J50: Dạ, em đã ghi nhận anh/chị đặt **3 phòng Deluxe**. Tuy nhiên, anh/chị chưa chọn chi nhánh và thời gian lưu trú ạ. Chuỗi Khách sạn Sen Việt Luxury hiện có các chi nhánh sau: 1. Sen Việt Sài Gòn (123 Lê Lợi, Quận 1, TP. HCM) 2. Sen Việt Hà Nội (45 Tràng Tiền, Hoàn Kiếm, Hà Nội) 3. Sen Việt Đà Nẵng (Võ Nguyên Giáp, Ngũ Hành Sơn, Đà Nẵng) 4. Sen Việt Nha Trang (Trần Phú, Lộc Thọ, Nha Trang, Khánh Hòa) 5. Sen Việt Đà Lạt (Trần Hưng Đạo, Phường 10, Đà Lạt, Lâm Đồng) 6. Sen Việt Gò Công (Đường Nguyễn Trãi, TX. Gò Công, Tiền Giang) 7. Sen Việt An Nhơn (Đường Quang Trung, TX. An Nhơn, Bình Định) Anh/chị muốn đặt phòng tại chi nhánh nào, dự kiến ngày nhận phòng, ngày trả phòng và số lượng khách (người lớn/trẻ em) là bao nhiêu để em kiểm tra phòng trống chính xác giúp mình nhé ạ? | K50: Pass | L50: Deterministic checks PASSED
A51: VA-16 | B51: Kiểm tra dữ liệu đầu vào | C51: P2 | D51: Edge | E51: Trẻ em: hỏi độ tuổi khi chính sách yêu cầu | F51: Phiên chat mới, còn phòng, chưa đăng nhập | G51: “2 người lớn 1 bé” | H51: Hỏi tuổi bé nếu giá/giường phụ phụ thuộc tuổi; nếu không thì không hỏi thừa. | J51: Dạ, em rất sẵn lòng hỗ trợ anh/chị đặt phòng tại chuỗi Khách sạn Sen Việt Luxury ạ! Để em có thể tư vấn phòng phù hợp nhất cho 2 người lớn và 1 bé, anh/chị vui lòng cho em xin thêm thông tin: 1. Mình muốn đặt phòng ở **chi nhánh nào** ạ? (Ví dụ: Hà Nội, Đà Lạt, Sài Gòn, Đà Nẵng, Nha Trang, Gò Công, An Nhơn...) 2. Ngày **check-in** (nhận phòng) và **check-out** (trả phòng) dự kiến của mình là ngày nào ạ? | K51: Pass | L51: Deterministic checks PASSED
A52: AV-01 | B52: Phòng trống / hết phòng | C52: P0 | D52: Negative | E52: Hết phòng toàn bộ ở ngày đã chọn | F52: Phiên chat mới, còn phòng, chưa đăng nhập | G52: Ngày kín phòng | H52: Bot không hiển thị card; thông báo hết phòng và gợi ý ngày gần nhất còn phòng hoặc chi nhánh khác. | I52: check_availability | J52: Dạ, em xin phép kiểm tra danh sách các chi nhánh hiện có của hệ thống khách sạn Sen Việt Luxury để hỗ trợ quý khách xem thông tin chi tiết ạ. Quý khách vui lòng đợi em một lát nhé! | K52: Pass | L52: Deterministic checks PASSED
A53: AV-02 | B53: Phòng trống / hết phòng | C53: P1 | D53: Edge | E53: Chỉ còn 1 phòng cuối | F53: Phiên chat mới, còn phòng, chưa đăng nhập | G53: Card Deluxe còn 1 | H53: Card hiển thị “chỉ còn 1 phòng”; bot không tạo áp lực quá mức nhưng nhắc nhẹ nên chốt sớm. | I53: check_availability | J53: Dạ, hiện tại chuỗi Khách sạn Sen Việt Luxury của chúng em có các chi nhánh sau: 1. Sen Việt Sài Gòn (Quận 1, TP. HCM) 2. Sen Việt Hà Nội (Hoàn Kiếm, Hà Nội) 3. Sen Việt Đà Nẵng (Ngũ Hành Sơn, Đà Nẵng) 4. Sen Việt Nha Trang (Nha Trang, Khánh Hòa) 5. Sen Việt Đà Lạt (Đà Lạt, Lâm Đồng) 6. Sen Việt Gò Công (Tiền Giang) 7. Sen Việt An Nhơn (Bình Định) Quý khách muốn đặt phòng tại chi nhánh nào để em hỗ trợ kiểm tra phòng Deluxe và các loại phòng trống cho mình ạ? | K53: Pass | L53: Deterministic checks PASSED
A54: AV-03 | B54: Phòng trống / hết phòng | C54: P0 | D54: Edge | E54: Phòng bị người khác đặt trong lúc khách đang nhập thông tin | F54: Phiên chat mới, còn phòng, chưa đăng nhập | G54: Khách đang bước 4, phòng bị đặt mất | H54: Khi create_booking thất bại do hết phòng: thông báo, không tạo QR, đề xuất phòng tương tự/ngày khác, giữ các slot khác. | I54: create_booking | J54: Dạ, em rất tiếc về sự bất tiện khi phòng quý khách vừa chọn có thể đã có khách khác nhanh tay đặt mất hoặc hết chỗ trong thời gian giữ phòng ạ! Để em kiểm tra lại tình trạng phòng trống ngay cho anh/chị nhé. Anh/chị vui lòng cho em xin lại thông tin chi nhánh, ngày nhận/trả phòng và số lượng khách để em hỗ trợ mình chọn lại phòng hoặc tìm hạng phòng thay thế phù hợp nhất ạ! Hiện tại chuỗi Khách sạn Sen Việt Luxury của chúng em có các chi nhánh sau: 1. Sen Việt Sài Gòn 2. Sen Việt Hà Nội 3. Sen Việt Đà Nẵng 4. Sen Việt Nha Trang 5. Sen Việt Đà Lạt 6. Sen Việt Gò Công 7. Sen Việt An Nhơn Anh/chị muốn đặt phòng tại chi nhánh nào ạ? | K54: Pass | L54: Deterministic checks PASSED
A55: AV-04 | B55: Phòng trống / hết phòng | C55: P1 | D55: Edge | E55: Không có phòng đủ sức chứa | F55: Phiên chat mới, còn phòng, chưa đăng nhập | G55: “6 người” nhưng phòng lớn nhất 4 người | H55: Đề xuất đặt 2 phòng; hiển thị phương án ghép phòng hợp lý. | I55: check_availability | J55: Dạ em chào anh/chị ạ! Đúng như anh/chị lưu ý, sức chứa tối đa của một phòng đơn (hạng Family) tại hệ thống Khách sạn Sen Việt Luxury của bên em là **4 người lớn**. Đối với đoàn **6 người**, để đảm bảo sự thoải mái và tiện nghi nhất, em xin gợi ý 2 phương án chia phòng để mình có thể chốt ngay trên chat luôn ạ: - **Phương án 1 (Khuyên dùng):** Đặt **1 phòng Family** (tối đa 4 người) + **1 phòng Deluxe** (2 người). - **Phương án 2:** Đặt **3 phòng Standard** hoặc **3 phòng Deluxe** (mỗi phòng 2 người). Không biết anh/chị muốn chọn phương án nào để em hỗ trợ kiểm tra phòng trống và tiến hành đặt phòng luôn cho mình ạ? Nếu mình đã sẵn sàng, anh/chị vui lòng cho em xin thêm thông tin **chi nhánh khách sạn** mà mình muốn ghé thăm nhé! | K55: Pass | L55: Deterministic checks PASSED
A56: AV-05 | B56: Phòng trống / hết phòng | C56: P1 | D56: Edge | E56: Gợi ý chi nhánh khác khi hết phòng | F56: Phiên chat mới, còn phòng, chưa đăng nhập | G56: CN Q1 hết, CN Đà Nẵng còn | H56: Bot hỏi khách có muốn xem chi nhánh khác, chỉ hiển thị chi nhánh còn phòng. | I56: check_availability | J56: Dạ, em xin phép gọi danh sách các chi nhánh hiện có của Sen Việt Luxury để anh/chị xem xét và lựa chọn chi nhánh phù hợp nhất ạ. | K56: Pass | L56: Deterministic checks PASSED
A57: AV-06 | B57: Phòng trống / hết phòng | C57: P0 | D57: Edge | E57: Giá thay đổi theo ngày (cuối tuần/lễ) | F57: Phiên chat mới, còn phòng, chưa đăng nhập | G57: Lưu trú đi qua đêm thứ Bảy hoặc ngày lễ | H57: Tổng tiền cộng đúng giá từng đêm, không nhân đều một giá; bot nêu rõ phụ thu nếu có. | I57: calculate_price | J57: Dạ, em xin gửi quý khách danh sách các chi nhánh của hệ thống Khách sạn Sen Việt Luxury ạ: 1. **Sen Việt Sài Gòn** (123 Lê Lợi, Quận 1, TP. Hồ Chí Minh) 2. **Sen Việt Hà Nội** (45 Tràng Tiền, Hoàn Kiếm, Hà Nội) 3. **Sen Việt Đà Nẵng** (Võ Nguyên Giáp, Ngũ Hành Sơn, Đà Nẵng) 4. **Sen Việt Nha Trang** (Trần Phú, Lộc Thọ, Nha Trang, Khánh Hòa) 5. **Sen Việt Đà Lạt** (Trần Hưng Đạo, Phường 10, Đà Lạt, Lâm Đồng) 6. **Sen Việt Gò Công** (Đường Nguyễn Trãi, TX. Gò Công, Tiền Giang) 7. **Sen Việt An Nhơn** (Đường Quang Trung, TX. An Nhơn, Bình Định) Anh/chị muốn lựa chọn dừng chân tại chi nhánh nào để em hỗ trợ kiểm tra phòng trống cho ngày cuối tuần (đi qua đêm thứ Bảy) ạ? | K57: Pass | L57: Deterministic checks PASSED
A58: AV-07 | B58: Phòng trống / hết phòng | C58: P1 | D58: Negative | E58: Phòng đang bảo trì/ẩn không được hiện | F58: Phiên chat mới, còn phòng, chưa đăng nhập | G58: Có phòng trạng thái MAINTENANCE | H58: Không xuất hiện trong card, không tính vào số lượng còn lại. | I58: check_availability | J58: Dạ, các phòng được phục vụ tại chuỗi Khách sạn Sen Việt Luxury luôn được kiểm tra và bảo dưỡng kỹ lưỡng trước khi đón tiếp quý khách ạ. Em xin phép gửi danh sách các chi nhánh hiện có của Sen Việt Luxury để anh/chị lựa chọn: 1. Sen Việt Sài Gòn (123 Lê Lợi, Quận 1, TP. Hồ Chí Minh) 2. Sen Việt Hà Nội (45 Tràng Tiền, Hoàn Kiếm, Hà Nội) 3. Sen Việt Đà Nẵng (Võ Nguyên Giáp, Ngũ Hành Sơn, Đà Nẵng) 4. Sen Việt Nha Trang (Trần Phú, Lộc Thọ, Nha Trang, Khánh Hòa) 5. Sen Việt Đà Lạt (Trần Hưng Đạo, Phường 10, Đà Lạt, Lâm Đồng) 6. Sen Việt Gò Công (Đường Nguyễn Trãi, TX. Gò Công, Tiền Giang) 7. Sen Việt An Nhơn (Đường Quang Trung, TX. An Nhơn, Bình Định) Anh/chị muốn đặt phòng tại chi nhánh nào ạ? | K58: Pass | L58: Deterministic checks PASSED
A59: GU-01 | B59: Thông tin khách | C59: P1 | D59: Edge | E59: Đặt hộ người khác | F59: Phiên chat mới, còn phòng, chưa đăng nhập | G59: “đặt cho bạn mình, tên Nam, 0988…” | H59: Bot hỏi/ghi nhận người ở khác người đặt; liên hệ xác nhận gửi cho ai. | J59: Dạ, em xin phép được tiếp nhận thông tin đặt phòng cho anh Nam. Anh/chị vui lòng cho em xin số điện thoại đầy đủ của anh Nam, cũng như thông tin về **chi nhánh khách sạn Sen Việt**, **ngày nhận phòng, ngày trả phòng** và **số lượng khách** (người lớn, trẻ em) để em tiến hành kiểm tra phòng trống cho mình nhé ạ! | K59: Pass | L59: Deterministic checks PASSED
A60: GU-02 | B60: Thông tin khách | C60: P1 | D60: Edge | E60: Khách không muốn cung cấp SĐT/email | F60: Phiên chat mới, còn phòng, chưa đăng nhập | G60: “không cho số điện thoại đâu” | H60: Giải thích lý do cần (xác nhận booking, liên hệ); nếu trường bắt buộc thì không tiếp tục; không ép buộc quá mức. | J60: Dạ em hiểu ạ! Tuy nhiên, để hệ thống có thể lưu lại thông tin đặt phòng và gửi xác nhận cho anh/chị, em rất cần số điện thoại liên lạc ạ. Anh/chị cứ yên tâm rằng thông tin của mình sẽ được bảo mật hoàn toàn theo chính sách của khách sạn Sen Việt Luxury. Anh/chị cho em xin lại số điện thoại nhé ạ? | K60: Pass | L60: Deterministic checks PASSED
A61: GU-03 | B61: Thông tin khách | C61: P2 | D61: Edge | E61: Đã đăng nhập nhưng thiếu SĐT | F61: Đã đăng nhập, hồ sơ thiếu SĐT | G61: Hồ sơ không có SĐT | H61: Chỉ hỏi SĐT, các thông tin khác dùng từ hồ sơ. | J61: Dạ, em chào anh/chị! Hiện tại chuỗi Khách sạn Sen Việt Luxury của chúng em có các chi nhánh sau: 1. **Sen Việt Sài Gòn** (123 Lê Lợi, Quận 1, TP. Hồ Chí Minh) 2. **Sen Việt Hà Nội** (45 Tràng Tiền, Hoàn Kiếm, Hà Nội) 3. **Sen Việt Đà Nẵng** (Võ Nguyên Giáp, Ngũ Hành Sơn, Đà Nẵng) 4. **Sen Việt Nha Trang** (Trần Phú, Lộc Thọ, Nha Trang, Khánh Hòa) 5. **Sen Việt Đà Lạt** (Trần Hưng Đạo, Phường 10, Đà Lạt, Lâm Đồng) 6. **Sen Việt Gò Công** (Đường Nguyễn Trãi, TX. Gò Công, Tiền Giang) 7. **Sen Việt An Nhơn** (Đường Quang Trung, TX. An Nhơn, Bình Định) Anh/chị muốn đặt phòng tại chi nhánh nào ạ? | K61: Pass | L61: Deterministic checks PASSED
A62: SV-01 | B62: Dịch vụ đi kèm | C62: P0 | D62: Happy | E62: Chọn nhiều dịch vụ | F62: Phiên chat mới, còn phòng, chưa đăng nhập | G62: “spa và đưa đón sân bay” | H62: Cả 2 được thêm, tổng tiền đúng, xuất hiện trong tóm tắt. | I62: list_services, calculate_price | J62: Dạ, em rất tiếc hiện tại hệ thống chưa ghi nhận chi nhánh khách sạn mà anh/chị muốn đặt (spa và đưa đón sân bay là các dịch vụ đi kèm). Anh/chị vui lòng cho em biết mình muốn đặt phòng tại chi nhánh nào trong hệ thống của Sen Việt Luxury nhé ạ: 1. Sen Việt Sài Gòn 2. Sen Việt Hà Nội 3. Sen Việt Đà Nẵng 4. Sen Việt Nha Trang 5. Sen Việt Đà Lạt 6. Sen Việt Gò Công 7. Sen Việt An Nhơn Em chờ thông tin từ anh/chị để hỗ trợ mình tiếp tục ạ! | K62: Pass | L62: Deterministic checks PASSED
A63: SV-02 | B63: Dịch vụ đi kèm | C63: P0 | D63: Happy | E63: Từ chối dịch vụ bằng nhiều cách nói | F63: Phiên chat mới, còn phòng, chưa đăng nhập | G63: “không”, “không cần”, “thôi”, “bỏ qua”, “khỏi”, “no” | H63: Mọi cách nói đều hiểu là không dùng dịch vụ, sang bước tiếp theo. | J63: Dạ, em hiểu rồi ạ. Nếu anh/chị không cần thêm dịch vụ hay mã giảm giá nào khác, em xin phép tiếp tục quá trình đặt phòng cho mình nhé. Quý khách vui lòng cho em xin tên và số điện thoại liên hệ để em hoàn tất thông tin đặt phòng ạ? | K63: Pass | L63: Deterministic checks PASSED
A64: SV-03 | B64: Dịch vụ đi kèm | C64: P1 | D64: Edge | E64: Hỏi chi tiết dịch vụ giữa chừng | F64: Phiên chat mới, còn phòng, chưa đăng nhập | G64: “spa gồm những gì, giá sao?” | H64: Trả lời từ dữ liệu thật, rồi nhắc quay lại bước chọn dịch vụ. | I64: search_faq / list_services | J64: Dạ, dịch vụ spa tại các chi nhánh của Sen Việt Luxury thường bao gồm các gói chăm sóc cơ thể thư giãn, massage trị liệu toàn thân, chăm sóc da mặt chuyên sâu... với mức giá dao động tùy theo từng gói dịch vụ và chi nhánh ạ. Em xin phép được hỏi anh/chị đang quan tâm đến chi nhánh nào của Sen Việt Luxury để em có thể kiểm tra danh sách dịch vụ chi tiết và chính xác nhất cho mình nha? | K64: Pass | L64: Deterministic checks PASSED
A65: SV-04 | B65: Dịch vụ đi kèm | C65: P1 | D65: Negative | E65: Chọn dịch vụ không tồn tại ở chi nhánh | F65: Phiên chat mới, còn phòng, chưa đăng nhập | G65: “cho mình karaoke” (chi nhánh không có) | H65: Báo không có, hiển thị lại danh sách dịch vụ thực tế; không bịa. | I65: list_services | J65: Dạ, hiện tại quý khách chưa chọn chi nhánh khách sạn nào để đặt phòng. Em xin gửi danh sách các chi nhánh thuộc chuỗi Khách sạn Sen Việt Luxury để anh/chị lựa chọn: 1. Sen Việt Sài Gòn (123 Lê Lợi, Quận 1, TP. Hồ Chí Minh) 2. Sen Việt Hà Nội (45 Tràng Tiền, Hoàn Kiếm, Hà Nội) 3. Sen Việt Đà Nẵng (Võ Nguyên Giáp, Ngũ Hành Sơn, Đà Nẵng) 4. Sen Việt Nha Trang (Trần Phú, Lộc Thọ, Nha Trang, Khánh Hòa) 5. Sen Việt Đà Lạt (Trần Hưng Đạo, Phường 10, Đà Lạt, Lâm Đồng) 6. Sen Việt Gò Công (Đường Nguyễn Trãi, TX. Gò Công, Tiền Giang) 7. Sen Việt An Nhơn (Đường Quang Trung, TX. An Nhơn, Bình Định) Anh/chị muốn đặt phòng tại chi nhánh nào ạ? | K65: Pass | L65: Deterministic checks PASSED
A66: SV-05 | B66: Dịch vụ đi kèm | C66: P0 | D66: Edge | E66: Dịch vụ tính theo người/đêm/lượt | F66: Phiên chat mới, còn phòng, chưa đăng nhập | G66: Ăn sáng tính theo người × đêm | H66: Tính tiền đúng quy tắc từng dịch vụ (VD 2 người × 2 đêm × giá). | I66: calculate_price | J66: Dạ, em xin phép giải đáp thắc mắc của anh/chị về chính sách ăn sáng tại chuỗi khách sạn Sen Việt Luxury ạ: - Theo quy định của khách sạn, tất cả các hạng phòng đều có giá niêm yết là giá phòng đơn thuần (Room Only) và **không bao gồm** bữa sáng. - Nếu quý khách có nhu cầu dùng bữa sáng, dịch vụ này sẽ được tính phụ thu theo số lượng người và số đêm lưu trú thực tế. Quý khách có thể chọn thêm dịch vụ ăn sáng khi tiến hành đặt phòng hoặc mua trực tiếp tại quầy lễ tân ạ. Bây giờ, em mời anh/chị tiếp tục quy trình đặt phòng nhé. Dạ, hiện tại chuỗi khách sạn Sen Việt Luxury của chúng em có các chi nhánh tại: 1. Sen Việt An Nhơn (Bình Định) 2. Sen Việt Đà Nẵng 3. Sen Việt Đà Lạt 4. Sen Việt Hà Nội 5. Sen Việt Sài Gòn Anh/chị muốn lựa chọn dừng chân tại chi nhánh nào ạ? Để em lấy danh sách giúp mình nhé! | K66: Pass | L66: Deterministic checks PASSED
A67: SV-06 | B67: Dịch vụ đi kèm | C67: P1 | D67: Edge | E67: Chọn số lượng dịch vụ | F67: Phiên chat mới, còn phòng, chưa đăng nhập | G67: “2 suất ăn sáng mỗi ngày” | H67: Lưu số lượng, tính đúng; nếu mơ hồ thì hỏi lại. | J67: Dạ, theo quy định của khách sạn thì giá phòng chưa bao gồm bữa sáng ạ. Tuy nhiên, em có thể hỗ trợ anh/chị chọn thêm các dịch vụ đi kèm (như ăn sáng, spa, xe đưa đón...) ngay sau khi mình chọn xong hạng phòng và chi nhánh. Dạ, hiện tại chuỗi Khách sạn Sen Việt Luxury của em có các chi nhánh sau: 1. Sen Việt Sài Gòn (Quận 1, TP. Hồ Chí Minh) 2. Sen Việt Hà Nội (Hoàn Kiếm, Hà Nội) 3. Sen Việt Đà Nẵng (Ngũ Hành Sơn, Đà Nẵng) 4. Sen Việt Nha Trang (Nha Trang, Khánh Hòa) 5. Sen Việt Đà Lạt (Đà Lạt, Lâm Đồng) 6. Sen Việt Gò Công (Tiền Giang) 7. Sen Việt An Nhơn (Bình Định) Quý khách muốn đặt phòng tại chi nhánh nào ạ? | K67: Pass | L67: Deterministic checks PASSED
A68: SV-07 | B68: Dịch vụ đi kèm | C68: P2 | D68: Edge | E68: “Lấy hết” dịch vụ | F68: Phiên chat mới, còn phòng, chưa đăng nhập | G68: “lấy tất cả” | H68: Bot xác nhận lại danh sách và tổng tiền trước khi thêm. | J68: Dạ, chuỗi Khách sạn Sen Việt Luxury hiện có các chi nhánh sau ạ: 1. **Sen Việt Sài Gòn** (123 Lê Lợi, Quận 1, TP. Hồ Chí Minh) 2. **Sen Việt Hà Nội** (45 Tràng Tiền, Hoàn Kiếm, Hà Nội) 3. **Sen Việt Đà Nẵng** (Võ Nguyên Giáp, Ngũ Hành Sơn, Đà Nẵng) 4. **Sen Việt Nha Trang** (Trần Phú, Lộc Thọ, Nha Trang, Khánh Hòa) 5. **Sen Việt Đà Lạt** (Trần Hưng Đạo, Phường 10, Đà Lạt, Lâm Đồng) 6. **Sen Việt Gò Công** (Đường Nguyễn Trãi, TX. Gò Công, Tiền Giang) 7. **Sen Việt An Nhơn** (Đường Quang Trung, TX. An Nhơn, Bình Định) Anh/chị muốn đặt phòng tại chi nhánh nào ạ? | K68: Pass | L68: Deterministic checks PASSED
A69: SV-08 | B69: Dịch vụ đi kèm | C69: P2 | D69: Edge | E69: Chi nhánh không có dịch vụ nào | F69: Phiên chat mới, còn phòng, chưa đăng nhập | G69: list_services trả rỗng | H69: Bot bỏ qua bước dịch vụ, không hiện card rỗng. | I69: list_services | J69: Dạ, em chào anh/chị! Chúc anh/chị một ngày tốt lành. Hiện tại, Khách sạn Sen Việt Luxury của chúng em có các chi nhánh sau: 1. **Sen Việt Sài Gòn** (123 Lê Lợi, Quận 1, TP. Hồ Chí Minh) 2. **Sen Việt Hà Nội** (45 Tràng Tiền, Hoàn Kiếm, Hà Nội) 3. **Sen Việt Đà Nẵng** (Võ Nguyên Giáp, Ngũ Hành Sơn, Đà Nẵng) 4. **Sen Việt Nha Trang** (Trần Phú, Lộc Thọ, Nha Trang, Khánh Hòa) 5. **Sen Việt Đà Lạt** (Trần Hưng Đạo, Phường 10, Đà Lạt, Lâm Đồng) 6. **Sen Việt Gò Công** (Đường Nguyễn Trãi, TX. Gò Công, Tiền Giang) 7. **Sen Việt An Nhơn** (Đường Quang Trung, TX. An Nhơn, Bình Định) Anh/chị muốn đặt phòng tại chi nhánh nào ạ? | K69: Pass | L69: Deterministic checks PASSED
A70: PR-01 | B70: Khuyến mãi / mã giảm giá | C70: P0 | D70: Happy | E70: Hiển thị mã hợp lệ | F70: Phiên chat mới, còn phòng, chưa đăng nhập | G70: Tới bước mã giảm giá | H70: Chỉ hiện các mã hợp lệ cho đơn hiện tại (hạn, điều kiện tối thiểu, phạm vi, lượt dùng). | I70: list_valid_promotions | J70: Dạ, hiện tại chuỗi Khách sạn Sen Việt Luxury đang có các mã khuyến mãi sau ạ: - **SUMMER2026**: Giảm 10% tổng giá trị đơn hàng. - **VIP500**: Giảm trực tiếp 500.000 VNĐ. - **DEMO2K**: Mã thử nghiệm thanh toán (giảm toàn bộ và đưa đơn về 2.000 VNĐ). - **SEN10**: Giảm 10%. - **VIP20**: Giảm 20%. - **MAX300K**: Giảm 50%. Dạ anh/chị muốn em áp dụng mã khuyến mãi nào cho đơn hàng của mình ạ? | K70: Pass | L70: Deterministic checks PASSED
A71: PR-02 | B71: Khuyến mãi / mã giảm giá | C71: P1 | D71: Edge | E71: Không có mã hợp lệ | F71: Phiên chat mới, còn phòng, chưa đăng nhập | G71: list_valid_promotions rỗng | H71: Báo hiện chưa có mã phù hợp, tiếp tục luồng, không bịa mã. | I71: list_valid_promotions | J71: Dạ, chuỗi Khách sạn Sen Việt Luxury hiện có các chi nhánh sau ạ: 1. Sen Việt Sài Gòn (123 Lê Lợi, Quận 1, TP. Hồ Chí Minh) 2. Sen Việt Hà Nội (45 Tràng Tiền, Hoàn Kiếm, Hà Nội) 3. Sen Việt Đà Nẵng (Võ Nguyên Giáp, Ngũ Hành Sơn, Đà Nẵng) 4. Sen Việt Nha Trang (Trần Phú, Lộc Thọ, Nha Trang, Khánh Hòa) 5. Sen Việt Đà Lạt (Trần Hưng Đạo, Phường 10, Đà Lạt, Lâm Đồng) 6. Sen Việt Gò Công (Đường Nguyễn Trãi, TX. Gò Công, Tiền Giang) 7. Sen Việt An Nhơn (Đường Quang Trung, TX. An Nhơn, Bình Định) Quý khách muốn đặt phòng tại chi nhánh nào để em hỗ trợ tiếp cho mình ạ? | K71: Pass | L71: Deterministic checks PASSED
A72: PR-03 | B72: Khuyến mãi / mã giảm giá | C72: P0 | D72: Happy | E72: Nhập mã thủ công đúng | F72: Phiên chat mới, còn phòng, chưa đăng nhập | G72: “áp mã SEN10” | H72: Validate qua tool, áp giảm, hiển thị tổng mới. | I72: list_valid_promotions, calculate_price | J72: Dạ, hiện tại anh/chị chưa chọn chi nhánh và phòng nghỉ, nên em chưa thể áp dụng mã giảm giá này vào đơn hàng được ạ. Em xin gửi anh/chị danh sách các chi nhánh hiện có của chuỗi Khách sạn Sen Việt Luxury: 1. Sen Việt Sài Gòn (123 Lê Lợi, Quận 1, TP. Hồ Chí Minh) 2. Sen Việt Hà Nội (45 Tràng Tiền, Hoàn Kiếm, Hà Nội) 3. Sen Việt Đà Nẵng (Võ Nguyên Giáp, Ngũ Hành Sơn, Đà Nẵng) 4. Sen Việt Nha Trang (Trần Phú, Lộc Thọ, Nha Trang, Khánh Hòa) 5. Sen Việt Đà Lạt (Trần Hưng Đạo, Phường 10, Đà Lạt, Lâm Đồng) 6. Sen Việt Gò Công (Đường Nguyễn Trãi, TX. Gò Công, Tiền Giang) 7. Sen Việt An Nhơn (Đường Quang Trung, TX. An Nhơn, Bình Định) Anh/chị muốn đặt phòng tại chi nhánh nào để em hỗ trợ mình kiểm tra phòng trống nhé ạ? | K72: Pass | L72: Deterministic checks PASSED
A73: PR-04 | B73: Khuyến mãi / mã giảm giá | C73: P0 | D73: Negative | E73: Mã không tồn tại | F73: Phiên chat mới, còn phòng, chưa đăng nhập | G73: “áp mã ABCXYZ” | H73: Báo mã không đúng, mời nhập lại hoặc chọn mã trong danh sách. | J73: Dạ, mã khuyến mãi **ABCXYZ** hiện không có trong danh sách mã hợp lệ của hệ thống Sen Việt Luxury ạ. Các mã khuyến mãi hiện đang khả dụng của chúng em gồm có: - **SUMMER2026**: Giảm 10% tổng hóa đơn. - **VIP500**: Giảm 500.000 VNĐ. - **DEMO2K**: Mã thử nghiệm thanh toán nhanh (giảm toàn bộ số tiền còn đúng 2.000 VNĐ). Quý khách có muốn em áp dụng một trong các mã hợp lệ trên hoặc chọn chi nhánh để tiếp tục đặt phòng không ạ? | K73: Pass | L73: Deterministic checks PASSED
A74: PR-05 | B74: Khuyến mãi / mã giảm giá | C74: P0 | D74: Negative | E74: Mã hết hạn | F74: Phiên chat mới, còn phòng, chưa đăng nhập | G74: “áp mã TET2025” | H74: Báo mã đã hết hạn (nêu ngày hết hạn nếu có), gợi ý mã đang còn hiệu lực. | J74: Dạ em rất tiếc, mã khuyến mãi `TET2025` đã hết hạn sử dụng vào ngày 15/02/2025 nên hệ thống hiện không thể áp dụng cho đơn hàng của mình ạ. Dạ trước khi tiếp tục, anh/chị có muốn chọn chi nhánh khách sạn Sen Việt Luxury và ngày lưu trú để em kiểm tra phòng trống trước không ạ? Nếu anh/chị có mã giảm giá khác còn hiệu lực (ví dụ như mã `DEMO2K` để thử nghiệm), hãy cho em biết nhé ạ! | K74: Pass | L74: Deterministic checks PASSED
A75: PR-06 | B75: Khuyến mãi / mã giảm giá | C75: P0 | D75: Negative | E75: Đơn chưa đạt giá trị tối thiểu | F75: Phiên chat mới, còn phòng, chưa đăng nhập | G75: Mã yêu cầu đơn ≥ 2.000.000đ, đơn hiện 1.500.000đ | H75: Nêu rõ cần thêm bao nhiêu (500.000đ) hoặc gợi ý thêm đêm/dịch vụ; không áp mã. | J75: Dạ, để đạt giá trị đơn hàng từ 2.000.000đ trở lên cho các yêu cầu thử nghiệm, em xin phép áp dụng mã khuyến mãi **DEMO2K** hoặc các mã giảm giá khác giúp anh/chị nhé. Hiện tại đơn hàng của mình đang ở bước nào anh/chị nhỉ? Em xin phép được hỗ trợ anh/chị chọn chi nhánh và kiểm tra phòng trống ngay bây giờ ạ! | K75: Pass | L75: Deterministic checks PASSED
A76: PR-07 | B76: Khuyến mãi / mã giảm giá | C76: P1 | D76: Negative | E76: Mã không áp dụng cho chi nhánh/hạng phòng | F76: Phiên chat mới, còn phòng, chưa đăng nhập | G76: Mã chỉ cho Suite, khách chọn Standard | H76: Báo phạm vi áp dụng, không áp mã. | J76: Dạ, em hiểu rồi ạ! Nếu mã giảm giá hiện tại không áp dụng được cho hạng phòng Standard của mình, em sẽ hỗ trợ anh/chị chọn hạng phòng phù hợp hoặc chúng ta tiếp tục với hạng phòng Standard và chuyển sang bước tiếp theo nhé. Anh/chị có muốn em tiếp tục tạo đơn thanh toán cho hạng phòng Standard này không ạ? | K76: Pass | L76: Deterministic checks PASSED
A77: PR-08 | B77: Khuyến mãi / mã giảm giá | C77: P1 | D77: Negative | E77: Mã hết lượt hoặc khách đã dùng | F77: Phiên chat mới, còn phòng, chưa đăng nhập | G77: Mã giới hạn 1 lần/khách | H77: Báo mã đã hết lượt/đã sử dụng. | J77: Dạ, hiện tại chuỗi Khách sạn Sen Việt Luxury của chúng em có các chi nhánh sau: 1. Sen Việt Sài Gòn (123 Lê Lợi, Quận 1, TP. Hồ Chí Minh) 2. Sen Việt Hà Nội (45 Tràng Tiền, Hoàn Kiếm, Hà Nội) 3. Sen Việt Đà Nẵng (Võ Nguyên Giáp, Ngũ Hành Sơn, Đà Nẵng) 4. Sen Việt Nha Trang (Trần Phú, Lộc Thọ, Nha Trang, Khánh Hòa) 5. Sen Việt Đà Lạt (Trần Hưng Đạo, Phường 10, Đà Lạt, Lâm Đồng) 6. Sen Việt Gò Công (Đường Nguyễn Trãi, TX. Gò Công, Tiền Giang) 7. Sen Việt An Nhơn (Đường Quang Trung, TX. An Nhơn, Bình Định) Anh/chị muốn chọn lưu trú tại chi nhánh nào để em hỗ trợ mình kiểm tra phòng trống nhé ạ? | K77: Pass | L77: Deterministic checks PASSED
A78: PR-09 | B78: Khuyến mãi / mã giảm giá | C78: P1 | D78: Edge | E78: Hai mã cùng lúc | F78: Phiên chat mới, còn phòng, chưa đăng nhập | G78: “áp cả SEN10 và VIP20” | H78: Nếu không cộng dồn: giải thích và hỏi chọn 1 mã; nếu cộng dồn được thì tính đúng theo quy tắc. | J78: Dạ, hệ thống của Khách sạn Sen Việt Luxury hiện có các chi nhánh sau để anh/chị lựa chọn: 1. Sen Việt Sài Gòn (123 Lê Lợi, Quận 1, TP. Hồ Chí Minh) 2. Sen Việt Hà Nội (45 Tràng Tiền, Hoàn Kiếm, Hà Nội) 3. Sen Việt Đà Nẵng (Võ Nguyên Giáp, Ngũ Hành Sơn, Đà Nẵng) 4. Sen Việt Nha Trang (Trần Phú, Lộc Thọ, Nha Trang, Khánh Hòa) 5. Sen Việt Đà Lạt (Trần Hưng Đạo, Phường 10, Đà Lạt, Lâm Đồng) 6. Sen Việt Gò Công (Đường Nguyễn Trãi, TX. Gò Công, Tiền Giang) 7. Sen Việt An Nhơn (Đường Quang Trung, TX. An Nhơn, Bình Định) Anh/chị muốn đặt phòng tại chi nhánh nào ạ? | K78: Pass | L78: Deterministic checks PASSED
A79: PR-10 | B79: Khuyến mãi / mã giảm giá | C79: P1 | D79: Edge | E79: Giảm giá vượt mức tối đa/không để tổng âm | F79: Phiên chat mới, còn phòng, chưa đăng nhập | G79: Mã giảm 50% tối đa 300.000đ | H79: Áp trần giảm tối đa; tổng tiền không bao giờ < 0. | I79: calculate_price | J79: Dạ em xin lỗi anh/chị, hiện tại hệ thống bên em không có mã giảm giá nào giảm chính xác 50% tối đa 300.000đ ạ. Tuy nhiên, bên em đang có mã **MAX300K** với mức giảm 50% hoặc anh/chị có thể tham khảo các mã khuyến mãi khả dụng khác như **SUMMER2026** (giảm 10%), **VIP500** (giảm 500k), hay mã test **DEMO2K**. Hiện tại hệ thống của chúng ta chưa chọn chi nhánh và phòng. Dạ anh/chị muốn đặt phòng tại chi nhánh nào của Sen Việt Luxury ạ? Em xin phép gọi danh sách chi nhánh để anh/chị lựa chọn nhé! | K79: Pass | L79: Deterministic checks PASSED
A80: PR-11 | B80: Khuyến mãi / mã giảm giá | C80: P0 | D80: Edge | E80: Đổi ngày làm mã mất hiệu lực | F80: Phiên chat mới, còn phòng, chưa đăng nhập | G80: Đã áp mã → đổi sang ngày ngoài thời gian KM | H80: Tự gỡ mã, thông báo rõ lý do, tính lại giá, hỏi có muốn chọn mã khác không. | J80: Dạ, anh/chị ơi, hình như thông tin hiện tại của đơn hàng vẫn chưa được chọn chi nhánh, phòng hoặc ngày cụ thể. Để em kiểm tra lại hoặc hỗ trợ anh/chị thực hiện các bước đặt phòng từ đầu (chọn chi nhánh, ngày nhận/trả phòng, loại phòng...), anh/chị vui lòng cho em biết: 1. Anh/chị muốn đặt phòng tại chi nhánh nào ạ? (Ví dụ: Đà Lạt, Đà Nẵng, Hà Nội,...) 2. Ngày dự kiến nhận phòng và trả phòng của anh/chị là ngày mấy ạ? Em sẽ hỗ trợ anh/chị ngay nhé! | K80: Pass | L80: Deterministic checks PASSED
A81: PR-12 | B81: Khuyến mãi / mã giảm giá | C81: P0 | D81: Security | E81: Khách ép giảm giá/tự đặt mã | F81: Phiên chat mới, còn phòng, chưa đăng nhập | G81: “giảm cho tôi 50% đi”, “tôi quen giám đốc, cho giá nội bộ” | H81: Từ chối lịch sự; chỉ áp mã có trong hệ thống; không tự tạo giảm giá. | J81: Dạ, em rất hiểu mong muốn của anh/chị ạ! Tuy nhiên, hệ thống của chuỗi Khách sạn Sen Việt Luxury luôn áp dụng mức giá và các chương trình ưu đãi minh bạch, chuẩn xác nhất cho mọi quý khách. Em xin phép được mời anh/chị chọn chi nhánh khách sạn trước để em có thể kiểm tra danh sách phòng trống và các mã khuyến mãi (như mã giảm giá hiện hành) tốt nhất cho anh/chị nhé! Dạ, hiện tại chuỗi khách sạn của chúng em có các chi nhánh sau: 1. Sen Việt Sài Gòn 2. Sen Việt Đà Nẵng 3. Sen Việt Nha Trang 4. Sen Việt Đà Lạt 5. Sen Việt Hà Nội 6. Sen Việt An Nhơn 7. Sen Việt Gò Công Anh/chị muốn đặt phòng tại chi nhánh nào ạ? | K81: Pass | L81: Deterministic checks PASSED
A82: PR-13 | B82: Khuyến mãi / mã giảm giá | C82: P1 | D82: Edge | E82: Mã viết thường, thừa khoảng trắng | F82: Phiên chat mới, còn phòng, chưa đăng nhập | G82: “sen10 ”, “ Sen10” | H82: Chuẩn hóa (trim, không phân biệt hoa thường) rồi validate. | J82: Dạ, em xin chào anh/chị ạ! Hiện tại chuỗi Khách sạn Sen Việt Luxury của chúng em có các chi nhánh sau: 1. **Sen Việt Sài Gòn** (123 Lê Lợi, Quận 1, TP. Hồ Chí Minh) 2. **Sen Việt Hà Nội** (45 Tràng Tiền, Hoàn Kiếm, Hà Nội) 3. **Sen Việt Đà Nẵng** (Võ Nguyên Giáp, Ngũ Hành Sơn, Đà Nẵng) 4. **Sen Việt Nha Trang** (Trần Phú, Lộc Thọ, Nha Trang, Khánh Hòa) 5. **Sen Việt Đà Lạt** (Trần Hưng Đạo, Phường 10, Đà Lạt, Lâm Đồng) 6. **Sen Việt Gò Công** (Đường Nguyễn Trãi, TX. Gò Công, Tiền Giang) 7. **Sen Việt An Nhơn** (Đường Quang Trung, TX. An Nhơn, Bình Định) Anh/chị muốn lựa chọn dừng chân tại chi nhánh nào để em hỗ trợ mình kiểm tra phòng trống nhé ạ? | K82: Pass | L82: Deterministic checks PASSED
A83: PR-14 | B83: Khuyến mãi / mã giảm giá | C83: P2 | D83: Edge | E83: Hỏi mã nào lợi nhất | F83: Phiên chat mới, còn phòng, chưa đăng nhập | G83: “mã nào giảm nhiều nhất cho đơn này?” | H83: So sánh số tiền giảm thực tế từ tool, đề xuất mã tốt nhất. | I83: list_valid_promotions, calculate_price | J83: Dạ, hiện tại hệ thống Sen Việt Luxury đang có các mã khuyến mãi sau ạ: - **DEMO2K**: Mã thử nghiệm PayOS (giảm mạnh nhất, đưa giá trị đơn hàng về đúng 2.000 VNĐ). - **VIP20**: Giảm 20% tổng giá trị đơn hàng. - **VIP500**: Giảm 500.000 VNĐ trực tiếp vào hóa đơn. - **SUMMER2026** và **SEN10**: Giảm 10% tổng giá trị đơn hàng. Nếu anh/chị muốn dùng mã giảm nhiều nhất cho đơn này, mã **DEMO2K** hoặc **VIP500** (tùy thuộc vào tổng tiền phòng của anh/chị) sẽ là lựa chọn tối ưu. Dạ, không biết anh/chị đã chọn được chi nhánh và thời gian lưu trú chưa để em hỗ trợ mình kiểm tra phòng trống và áp mã luôn nhé ạ? | K83: Pass | L83: Deterministic checks PASSED
A84: CF-01 | B84: Xác nhận đặt phòng | C84: P0 | D84: Happy | E84: Các từ đồng nghĩa với “xác nhận” | F84: Phiên chat mới, còn phòng, chưa đăng nhập | G84: “xác nhận”, “ok”, “oke”, “đồng ý”, “chốt”, “đặt đi”, “yes”, “đúng rồi”, “👍” (ở bước xác nhận cuối) | H84: Tất cả được hiểu là xác nhận, chuyển sang chọn hình thức thanh toán. | J84: Dạ, em chào anh/chị! Chào mừng anh/chị đến với chuỗi Khách sạn Sen Việt Luxury. Hiện tại hệ thống của chúng em có các chi nhánh sau: 1. Sen Việt Sài Gòn (123 Lê Lợi, Quận 1, TP. Hồ Chí Minh) 2. Sen Việt Hà Nội (45 Tràng Tiền, Hoàn Kiếm, Hà Nội) 3. Sen Việt Đà Nẵng (Võ Nguyên Giáp, Ngũ Hành Sơn, Đà Nẵng) 4. Sen Việt Nha Trang (Trần Phú, Lộc Thọ, Nha Trang, Khánh Hòa) 5. Sen Việt Đà Lạt (Trần Hưng Đạo, Phường 10, Đà Lạt, Lâm Đồng) 6. Sen Việt Gò Công (Đường Nguyễn Trãi, TX. Gò Công, Tiền Giang) 7. Sen Việt An Nhơn (Đường Quang Trung, TX. An Nhơn, Bình Định) Anh/chị muốn đặt phòng tại chi nhánh nào ạ? | K84: Pass | L84: Deterministic checks PASSED
A85: CF-02 | B85: Xác nhận đặt phòng | C85: P0 | D85: Edge | E85: “ok” ở ngữ cảnh không phải bước xác nhận | F85: Phiên chat mới, còn phòng, chưa đăng nhập | G85: Bot đang hỏi “Bạn có muốn dùng dịch vụ không?” → khách: “ok” | H85: KHÔNG hiểu thành xác nhận đặt phòng; hỏi lại làm rõ (dùng dịch vụ nào / không). | J85: Dạ, chuỗi khách sạn Sen Việt Luxury của chúng em hiện có các chi nhánh sau ạ: 1. **Sen Việt Sài Gòn** (123 Lê Lợi, Quận 1, TP. Hồ Chí Minh) 2. **Sen Việt Hà Nội** (45 Tràng Tiền, Hoàn Kiếm, Hà Nội) 3. **Sen Việt Đà Nẵng** (Võ Nguyên Giáp, Ngũ Hành Sơn, Đà Nẵng) 4. **Sen Việt Nha Trang** (Trần Phú, Lộc Thọ, Nha Trang, Khánh Hòa) 5. **Sen Việt Đà Lạt** (Trần Hưng Đạo, Phường 10, Đà Lạt, Lâm Đồng) 6. **Sen Việt Gò Công** (Đường Nguyễn Trãi, TX. Gò Công, Tiền Giang) 7. **Sen Việt An Nhơn** (Đường Quang Trung, TX. An Nhơn, Bình Định) Anh/chị muốn lựa chọn chi nhánh nào để dừng chân ạ? | K85: Pass | L85: Deterministic checks PASSED
A86: CF-03 | B86: Xác nhận đặt phòng | C86: P0 | D86: Negative | E86: Từ mơ hồ không phải xác nhận | F86: Phiên chat mới, còn phòng, chưa đăng nhập | G86: “để mình xem”, “cũng được”, “hmm”, “chắc vậy” | H86: Không chuyển bước; hỏi lại ngắn gọn, kèm nút Xác nhận/Chỉnh sửa. | J86: Dạ, chuỗi Khách sạn Sen Việt Luxury hiện có các chi nhánh sau để anh/chị lựa chọn: 1. **Sen Việt Sài Gòn** (123 Lê Lợi, Quận 1, TP. Hồ Chí Minh) 2. **Sen Việt Hà Nội** (45 Tràng Tiền, Hoàn Kiếm, Hà Nội) 3. **Sen Việt Đà Nẵng** (Võ Nguyên Giáp, Ngũ Hành Sơn, Đà Nẵng) 4. **Sen Việt Nha Trang** (Trần Phú, Lộc Thọ, Nha Trang, Khánh Hòa) 5. **Sen Việt Đà Lạt** (Trần Hưng Đạo, Phường 10, Đà Lạt, Lâm Đồng) 6. **Sen Việt Gò Công** (Đường Nguyễn Trãi, TX. Gò Công, Tiền Giang) 7. **Sen Việt An Nhơn** (Đường Quang Trung, TX. An Nhơn, Bình Định) Anh/chị muốn đặt phòng tại chi nhánh nào ạ? | K86: Pass | L86: Deterministic checks PASSED
A87: CF-04 | B87: Xác nhận đặt phòng | C87: P0 | D87: Negative | E87: “Xác nhận” khi chưa đủ thông tin | F87: Phiên chat mới, còn phòng, chưa đăng nhập | G87: Chưa có SĐT mà gõ “xác nhận” | H87: Bot nêu rõ còn thiếu gì và hỏi bổ sung, không chuyển thanh toán. | J87: Dạ, để em có thể hỗ trợ anh/chị tiến hành đặt phòng và giữ chỗ, anh/chị vui lòng cung cấp cho em xin thông tin liên hệ bao gồm **Họ tên** và **Số điện thoại** trước nhé ạ! Hiện tại chuỗi Khách sạn Sen Việt Luxury của chúng em đang có các chi nhánh sau: 1. Sen Việt Sài Gòn (Quận 1, TP. Hồ Chí Minh) 2. Sen Việt Hà Nội (Hoàn Kiếm, Hà Nội) 3. Sen Việt Đà Nẵng (Ngũ Hành Sơn, Đà Nẵng) 4. Sen Việt Nha Trang (Nha Trang, Khánh Hòa) 5. Sen Việt Đà Lạt (Đà Lạt, Lâm Đồng) 6. Sen Việt Gò Công (Tiền Giang) 7. Sen Việt An Nhơn (Bình Định) Anh/chị muốn đặt phòng tại chi nhánh nào và đi vào ngày nào vậy ạ? | K87: Pass | L87: Deterministic checks PASSED
A88: CF-05 | B88: Xác nhận đặt phòng | C88: P0 | D88: Edge | E88: Xác nhận kèm yêu cầu sửa | F88: Phiên chat mới, còn phòng, chưa đăng nhập | G88: “ok nhưng đổi thành 3 người” | H88: Xử lý sửa trước, hiển thị tóm tắt mới, hỏi xác nhận lại; không chuyển bước. | J88: Dạ, em đã cập nhật lại số lượng khách thành 3 người lớn cho lịch trình ngày mai (14/10/2026 - 15/10/2026) tại chi nhánh Sen Việt Sài Gòn ạ. Hiện tại chi nhánh đang có hạng phòng **FAMILY** trống: - **Giá phòng**: 2.000.000 VNĐ/đêm (sức chứa tiêu chuẩn 4 người, rất thoải mái cho 3 anh/chị). Anh/chị có muốn em chọn loại phòng FAMILY này luôn không ạ? | K88: Pass | L88: Deterministic checks PASSED
A89: CF-06 | B89: Xác nhận đặt phòng | C89: P0 | D89: Negative | E89: Từ phủ định | F89: Phiên chat mới, còn phòng, chưa đăng nhập | G89: “không xác nhận”, “chưa”, “đừng”, “khoan” | H89: Không chuyển bước, hỏi khách muốn sửa gì. | J89: Dạ em hiểu ạ! Em xin phép dừng việc đặt phòng lại theo ý anh/chị. Nếu anh/chị cần hỗ trợ bất kỳ thông tin gì về các chi nhánh, giá phòng hay dịch vụ của Sen Việt Luxury, anh/chị cứ nhắn em nhé. Chúc anh/chị một ngày tốt lành ạ! | K89: Pass | L89: Deterministic checks PASSED
A90: CF-07 | B90: Xác nhận đặt phòng | C90: P0 | D90: Edge | E90: Xác nhận hai lần liên tiếp (double-click) | F90: Phiên chat mới, còn phòng, chưa đăng nhập | G90: Bấm “Xác nhận” 2 lần trong 1 giây | H90: Idempotent: chỉ tạo 1 booking, 1 QR. | I90: create_booking | J90: Dạ, em chào anh/chị ạ! Hệ thống của em hiện có các chi nhánh tuyệt vời sau của chuỗi Khách sạn Sen Việt Luxury: 1. **Sen Việt Sài Gòn** (Quận 1, TP. Hồ Chí Minh) 2. **Sen Việt Hà Nội** (Hoàn Kiếm, Hà Nội) 3. **Sen Việt Đà Nẵng** (Ngũ Hành Sơn, Đà Nẵng) 4. **Sen Việt Nha Trang** (Nha Trang, Khánh Hòa) 5. **Sen Việt Đà Lạt** (Đà Lạt, Lâm Đồng) 6. **Sen Việt Gò Công** (Tiền Giang) 7. **Sen Việt An Nhơn** (Bình Định) Anh/chị muốn lựa chọn dừng chân tại chi nhánh nào để em hỗ trợ mình kiểm tra phòng trống ạ? | K90: Pass | L90: Deterministic checks PASSED
A91: PM-01 | B91: Thanh toán (QR PayOS) | C91: P0 | D91: Happy | E91: QR chuyển khoản đúng thông tin | F91: Phiên chat mới, còn phòng, chưa đăng nhập | G91: Chọn chuyển khoản | H91: Card QR hiển thị: QR, đúng số tiền, nội dung = mã booking/orderCode, đồng hồ đếm ngược hold; booking PENDING_PAYMENT. | I91: create_booking, create_payment_qr | J91: Dạ em rất xin lỗi quý khách, hệ thống đặt phòng đang gặp chút sự cố kỹ thuật khi tạo mã thanh toán. Quý khách vui lòng cung cấp lại giúp em số điện thoại hoặc thông tin đặt phòng để em hỗ trợ kiểm tra và thực hiện lại giao dịch một cách nhanh nhất ạ! | K91: Pass | L91: Deterministic checks PASSED
A92: PM-02 | B92: Thanh toán (QR PayOS) | C92: P0 | D92: Happy | E92: Thanh toán thành công qua webhook | F92: Phiên chat mới, còn phòng, chưa đăng nhập | G92: Khách quét QR và chuyển đúng số tiền | H92: Hệ thống nhận webhook PayOS; bot tự thông báo thành công, hiển thị mã booking + tóm tắt mà khách không cần báo. | I92: get_payment_status | J92: Dạ, em ghi nhận thông tin! Anh/chị vui lòng đợi trong giây lát để hệ thống kiểm tra trạng thái giao dịch chuyển khoản ạ. Nếu anh/chị đã hoàn tất chuyển khoản thành công, giao diện sẽ tự động cập nhật xác nhận đặt phòng cho anh/chị nhé! | K92: Pass | L92: Deterministic checks PASSED
A93: PM-03 | B93: Thanh toán (QR PayOS) | C93: P0 | D93: Security | E93: Khách nói “đã chuyển rồi” nhưng chưa có giao dịch | F93: Phiên chat mới, còn phòng, chưa đăng nhập | G93: “mình chuyển rồi mà” | H93: Bot gọi get_payment_status; nếu chưa nhận được thì nói thật “chưa ghi nhận”, hướng dẫn chờ/kiểm tra; không tự xác nhận theo lời khách. | I93: get_payment_status | J93: Dạ, em chào anh/chị ạ! Em xin lỗi vì hệ thống bên em có thể chưa nhận được thông tin xác nhận chuyển khoản ngay lập tức. Để em kiểm tra lại giao dịch thanh toán cho đơn hàng của mình nhé. Anh/chị vui lòng đợi em một lát ạ! | K93: Pass | L93: Deterministic checks PASSED
A94: PM-04 | B94: Thanh toán (QR PayOS) | C94: P0 | D94: Negative | E94: QR hết hạn | F94: Phiên chat mới, còn phòng, chưa đăng nhập | G94: Quá thời gian hold | H94: Báo QR hết hạn, giải phóng phòng, hỏi tạo QR mới hay hủy; nếu còn phòng thì tạo QR mới với orderCode mới. | I94: create_payment_qr | J94: Dạ, theo quy định của hệ thống, thời gian giữ phòng tạm thời chờ thanh toán là **5 phút**. Nếu quá 5 phút mà đơn hàng chưa được thanh toán, hệ thống sẽ tự động hủy giữ phòng để nhường chỗ cho các khách hàng khác. Anh/chị có muốn em hỗ trợ kiểm tra lại phòng trống và đặt lại từ đầu không ạ? | K94: Pass | L94: Deterministic checks PASSED
A95: PM-05 | B95: Thanh toán (QR PayOS) | C95: P0 | D95: Negative | E95: Chuyển thiếu tiền | F95: Phiên chat mới, còn phòng, chưa đăng nhập | G95: Chuyển 1.000.000đ thay vì 1.500.000đ | H95: Báo số tiền chưa đủ, nêu số còn thiếu và cách xử lý (tạo QR bù/liên hệ lễ tân); không xác nhận booking. | I95: get_payment_status | J95: Dạ, em chào anh/chị! Số tiền thanh toán cho đơn đặt phòng của mình đã được hệ thống tính toán chính xác dựa trên giá phòng, số đêm và các dịch vụ (hoặc mã giảm giá) đã chọn ạ. Em không thể tự ý thay đổi số tiền thanh toán khi chưa có sự điều chỉnh từ hệ thống. Nếu anh/chị muốn giảm chi phí, em có thể hỗ trợ kiểm tra lại các mã giảm giá hiện hành hoặc điều chỉnh lại số lượng phòng/dịch vụ cho phù hợp với ngân sách của mình. Anh/chị có muốn em áp dụng mã khuyến mãi hoặc điều chỉnh lại thông tin đặt phòng không ạ? | K95: Pass | L95: Deterministic checks PASSED
A96: PM-06 | B96: Thanh toán (QR PayOS) | C96: P1 | D96: Negative | E96: Chuyển dư tiền | F96: Phiên chat mới, còn phòng, chưa đăng nhập | G96: Chuyển 2.000.000đ cho đơn 1.500.000đ | H96: Xác nhận booking nếu đủ, báo có khoản dư và chuyển nhân viên xử lý hoàn tiền theo chính sách. | J96: Dạ, em rất xin lỗi quý khách vì hệ thống đang gặp chút sự cố kỹ thuật nhỏ khi tạo đơn hàng. Anh/chị vui lòng cung cấp lại giúp em thông tin chi tiết về đơn đặt phòng (chi nhánh, ngày nhận/trả phòng, số lượng khách, thông tin liên hệ) để em tiến hành hỗ trợ anh/chị tạo lại đơn hàng một cách chính xác và nhanh chóng nhất nhé ạ! | K96: Pass | L96: Deterministic checks PASSED
A97: PM-07 | B97: Thanh toán (QR PayOS) | C97: P1 | D97: Negative | E97: Sai nội dung chuyển khoản | F97: Phiên chat mới, còn phòng, chưa đăng nhập | G97: Giao dịch không khớp orderCode | H97: Không tự khớp bừa; hướng dẫn gửi mã booking/ảnh giao dịch hoặc liên hệ nhân viên. | J97: Dạ, em rất xin lỗi quý khách về sự bất tiện này ạ! Để em hỗ trợ quý khách kiểm tra lại thông tin giao dịch và `orderCode`, quý khách vui lòng cung cấp giúp em **mã đơn hàng (orderCode)** hoặc **số điện thoại** đã dùng khi đặt phòng nhé. Em sẽ kiểm tra lại ngay cho anh/chị ạ! | K97: Pass | L97: Deterministic checks PASSED
A98: PM-08 | B98: Thanh toán (QR PayOS) | C98: P0 | D98: Negative | E98: Thanh toán thất bại/PayOS lỗi | F98: Phiên chat mới, còn phòng, chưa đăng nhập | G98: PayOS trả lỗi | H98: Xin lỗi, báo lỗi dễ hiểu, cho thử lại hoặc chọn phương thức khác; booking không bị kẹt PENDING. | J98: Dạ, em rất xin lỗi quý khách về sự bất tiện khi hệ thống thanh toán qua PayOS gặp lỗi ạ. Anh/chị có thể thử tải lại trang hoặc chọn phương thức thanh toán trực tiếp tại quầy lễ tân (bằng tiền mặt hoặc thẻ POS) khi làm thủ tục nhận phòng (Check-in) để em hỗ trợ giữ phòng cho mình nhé ạ. Anh/chị cho em xin ý kiến để em đổi phương thức thanh toán giúp anh/chị nha? | K98: Pass | L98: Deterministic checks PASSED
A99: PM-09 | B99: Thanh toán (QR PayOS) | C99: P0 | D99: Edge | E99: Khách tải lại trang trong thời gian hold | F99: Phiên chat mới, còn phòng, chưa đăng nhập | G99: Đang hiện QR → F5 | H99: Khôi phục QR và đồng hồ đếm ngược đúng thời gian còn lại; không tạo booking mới. | I99: get_payment_status | J99: Blocked by design (frontend/external infrastructure requirement) | K99: Blocked | L99: Yêu cầu trình duyệt frontend: Kiểm thử khôi phục state khi F5 reload trang
A100: PM-10 | B100: Thanh toán (QR PayOS) | C100: P1 | D100: Negative | E100: Quay lại sau khi hold đã hết | F100: Phiên chat mới, còn phòng, chưa đăng nhập | G100: Quay lại sau 30 phút | H100: Báo đã hết hạn giữ phòng, kiểm tra phòng, đề xuất đặt lại kèm giữ nguyên thông tin cũ. | J100: Dạ vâng, em vẫn ở đây sẵn sàng hỗ trợ anh/chị bất cứ lúc nào. Khi nào anh/chị cần tiếp tục đặt phòng, cứ nhắn em nhé! | K100: Pass | L100: Deterministic checks PASSED
A101: PM-11 | B101: Thanh toán (QR PayOS) | C101: P1 | D101: Negative | E101: Phương thức không hỗ trợ | F101: Phiên chat mới, còn phòng, chưa đăng nhập | G101: “trả bằng Momo/thẻ/tiền mặt/trả góp được không?” | H101: Chỉ nêu đúng các phương thức hệ thống hỗ trợ; không hứa hẹn thứ không có. | J101: Dạ, hiện tại chuỗi Khách sạn Sen Việt Luxury hỗ trợ hai phương thức thanh toán chính là **Chuyển khoản ngân hàng** (bao gồm quét mã QR qua các ứng dụng ngân hàng/ví điện tử liên kết) và **Tiền mặt** ạ. Dạ, không biết anh/chị muốn chọn hình thức thanh toán nào để em hỗ trợ mình hoàn tất đơn đặt phòng nhé? | K101: Pass | L101: Deterministic checks PASSED
A102: PM-12 | B102: Thanh toán (QR PayOS) | C102: P1 | D102: Edge | E102: Hỏi hóa đơn VAT | F102: Phiên chat mới, còn phòng, chưa đăng nhập | G102: “xuất hóa đơn công ty được không?” | H102: Trả lời theo chính sách; nếu chưa hỗ trợ trên chat thì thu thập thông tin cơ bản và chuyển nhân viên. | J102: Dạ, khách sạn Sen Việt Luxury hoàn toàn hỗ trợ xuất hóa đơn điện tử (VAT) cho quý khách ạ! Quý khách có thể cung cấp thông tin xuất hóa đơn (tên công ty, mã số thuế, địa chỉ công ty, email nhận hóa đơn) cho em trong quá trình đặt phòng hoặc thông báo trực tiếp với lễ tân khi làm thủ tục check-in nhé ạ. Bây giờ, để em hỗ trợ quý khách đặt phòng, quý khách muốn chọn chi nhánh nào của Sen Việt Luxury ạ? (Hiện hệ thống có các chi nhánh tại Đà Lạt, Nha Trang, Đà Nẵng, Sài Gòn, Hà Nội, An Nhơn, Gò Công...). Em xin phép gửi danh sách các chi nhánh để quý khách lựa chọn nhé ạ! | K102: Pass | L102: Deterministic checks PASSED
A103: PM-13 | B103: Thanh toán (QR PayOS) | C103: P0 | D103: Edge | E103: Webhook đến 2 lần hoặc đến trễ | F103: Phiên chat mới, còn phòng, chưa đăng nhập | G103: PayOS gửi webhook trùng | H103: Xử lý idempotent: booking chỉ xác nhận 1 lần, không gửi 2 thông báo. | J103: Dạ, chuỗi Khách sạn Sen Việt Luxury của chúng em hiện có các chi nhánh sau: 1. **Sen Việt Sài Gòn** (123 Lê Lợi, Quận 1, TP. Hồ Chí Minh) 2. **Sen Việt Hà Nội** (45 Tràng Tiền, Hoàn Kiếm, Hà Nội) 3. **Sen Việt Đà Nẵng** (Võ Nguyên Giáp, Ngũ Hành Sơn, Đà Nẵng) 4. **Sen Việt Nha Trang** (Trần Phú, Lộc Thọ, Nha Trang, Khánh Hòa) 5. **Sen Việt Đà Lạt** (Trần Hưng Đạo, Phường 10, Đà Lạt, Lâm Đồng) 6. **Sen Việt Gò Công** (Đường Nguyễn Trãi, TX. Gò Công, Tiền Giang) 7. **Sen Việt An Nhơn** (Đường Quang Trung, TX. An Nhơn, Bình Định) Anh/chị muốn chọn chi nhánh nào để em kiểm tra phòng trống giúp mình ạ? | K103: Pass | L103: Deterministic checks PASSED
A104: PM-14 | B104: Thanh toán (QR PayOS) | C104: P0 | D104: Edge | E104: Tiền về sau khi hold đã hết (race) | F104: Phiên chat mới, còn phòng, chưa đăng nhập | G104: Khách chuyển ở giây cuối, hold vừa hết | H104: Nếu còn phòng: xác nhận booking; nếu phòng đã bị người khác giữ: báo rõ, hoàn tiền/chuyển nhân viên; không mất tiền khách. | J104: Dạ, em rất tiếc vì thời gian giữ phòng tạm thời đã hết. Để em hỗ trợ anh/chị kiểm tra lại phòng trống và tiến hành đặt phòng mới nhé! Hiện tại, hệ thống Khách sạn Sen Việt Luxury của chúng em có các chi nhánh sau: 1. Sen Việt Sài Gòn (123 Lê Lợi, Quận 1, TP. Hồ Chí Minh) 2. Sen Việt Hà Nội (45 Tràng Tiền, Hoàn Kiếm, Hà Nội) 3. Sen Việt Đà Nẵng (Võ Nguyên Giáp, Ngũ Hành Sơn, Đà Nẵng) 4. Sen Việt Nha Trang (Trần Phú, Lộc Thọ, Nha Trang, Khánh Hòa) 5. Sen Việt Đà Lạt (Trần Hưng Đạo, Phường 10, Đà Lạt, Lâm Đồng) 6. Sen Việt Gò Công (Đường Nguyễn Trãi, TX. Gò Công, Tiền Giang) 7. Sen Việt An Nhơn (Đường Quang Trung, TX. An Nhơn, Bình Định) Anh/chị muốn đặt phòng tại chi nhánh nào ạ? | K104: Pass | L104: Deterministic checks PASSED
A105: PM-15 | B105: Thanh toán (QR PayOS) | C105: P1 | D105: Edge | E105: Hỏi hoàn tiền sau khi đã thanh toán | F105: Phiên chat mới, còn phòng, chưa đăng nhập | G105: “hủy và hoàn tiền cho mình” | H105: Giải thích chính sách hoàn tiền, xác nhận trước khi hủy, thực hiện qua cancel_booking. | I105: cancel_booking | J105: Dạ, em xin gửi quy định về chính sách hủy phòng và hoàn tiền của Chuỗi Khách sạn Sen Việt như sau ạ: - **Hủy trước từ 7 ngày trở lên:** Hoàn tiền 100% số tiền đã thanh toán. - **Hủy từ 3 đến dưới 7 ngày:** Hoàn tiền 50% số tiền đã thanh toán. - **Hủy dưới 3 ngày nhận phòng hoặc vắng mặt (no-show):** Không hoàn tiền (0%). Dạ, không biết anh/chị có muốn em hỗ trợ kiểm tra thông tin đặt phòng hay cần tư vấn thêm vấn đề gì không ạ? | K105: Pass | L105: Deterministic checks PASSED
...

Sheet Tổng hợp
A1: Nhóm | B1: Tên nhóm | C1: Tổng | D1: Pass | E1: Fail | F1: Blocked | G1: Chưa test | H1: % Pass
A2: HP | B2: Luồng đặt phòng chuẩn | C2: =COUNTIF('Test Cases'!$A:$A,A2&"-*") | D2: =COUNTIFS('Test Cases'!$A:$A,$A2&"-*",'Test Cases'!$K:$K,"Pass") | E2: =COUNTIFS('Test Cases'!$A:$A,$A2&"-*",'Test Cases'!$K:$K,"Fail") | F2: =COUNTIFS('Test Cases'!$A:$A,$A2&"-*",'Test Cases'!$K:$K,"Blocked") | G2: =COUNTIFS('Test Cases'!$A:$A,$A2&"-*",'Test Cases'!$K:$K,"Chưa test") | H2: =IF(C2=0,0,D2/C2)
A3: SF | B3: Slot filling / khai báo gộp | C3: =COUNTIF('Test Cases'!$A:$A,A3&"-*") | D3: =COUNTIFS('Test Cases'!$A:$A,$A3&"-*",'Test Cases'!$K:$K,"Pass") | E3: =COUNTIFS('Test Cases'!$A:$A,$A3&"-*",'Test Cases'!$K:$K,"Fail") | F3: =COUNTIFS('Test Cases'!$A:$A,$A3&"-*",'Test Cases'!$K:$K,"Blocked") | G3: =COUNTIFS('Test Cases'!$A:$A,$A3&"-*",'Test Cases'!$K:$K,"Chưa test") | H3: =IF(C3=0,0,D3/C3)
A4: CH | B4: Đổi ý / sửa thông tin | C4: =COUNTIF('Test Cases'!$A:$A,A4&"-*") | D4: =COUNTIFS('Test Cases'!$A:$A,$A4&"-*",'Test Cases'!$K:$K,"Pass") | E4: =COUNTIFS('Test Cases'!$A:$A,$A4&"-*",'Test Cases'!$K:$K,"Fail") | F4: =COUNTIFS('Test Cases'!$A:$A,$A4&"-*",'Test Cases'!$K:$K,"Blocked") | G4: =COUNTIFS('Test Cases'!$A:$A,$A4&"-*",'Test Cases'!$K:$K,"Chưa test") | H4: =IF(C4=0,0,D4/C4)
A5: VA | B5: Kiểm tra dữ liệu đầu vào | C5: =COUNTIF('Test Cases'!$A:$A,A5&"-*") | D5: =COUNTIFS('Test Cases'!$A:$A,$A5&"-*",'Test Cases'!$K:$K,"Pass") | E5: =COUNTIFS('Test Cases'!$A:$A,$A5&"-*",'Test Cases'!$K:$K,"Fail") | F5: =COUNTIFS('Test Cases'!$A:$A,$A5&"-*",'Test Cases'!$K:$K,"Blocked") | G5: =COUNTIFS('Test Cases'!$A:$A,$A5&"-*",'Test Cases'!$K:$K,"Chưa test") | H5: =IF(C5=0,0,D5/C5)
A6: AV | B6: Phòng trống / hết phòng | C6: =COUNTIF('Test Cases'!$A:$A,A6&"-*") | D6: =COUNTIFS('Test Cases'!$A:$A,$A6&"-*",'Test Cases'!$K:$K,"Pass") | E6: =COUNTIFS('Test Cases'!$A:$A,$A6&"-*",'Test Cases'!$K:$K,"Fail") | F6: =COUNTIFS('Test Cases'!$A:$A,$A6&"-*",'Test Cases'!$K:$K,"Blocked") | G6: =COUNTIFS('Test Cases'!$A:$A,$A6&"-*",'Test Cases'!$K:$K,"Chưa test") | H6: =IF(C6=0,0,D6/C6)
A7: GU | B7: Thông tin khách | C7: =COUNTIF('Test Cases'!$A:$A,A7&"-*") | D7: =COUNTIFS('Test Cases'!$A:$A,$A7&"-*",'Test Cases'!$K:$K,"Pass") | E7: =COUNTIFS('Test Cases'!$A:$A,$A7&"-*",'Test Cases'!$K:$K,"Fail") | F7: =COUNTIFS('Test Cases'!$A:$A,$A7&"-*",'Test Cases'!$K:$K,"Blocked") | G7: =COUNTIFS('Test Cases'!$A:$A,$A7&"-*",'Test Cases'!$K:$K,"Chưa test") | H7: =IF(C7=0,0,D7/C7)
A8: SV | B8: Dịch vụ đi kèm | C8: =COUNTIF('Test Cases'!$A:$A,A8&"-*") | D8: =COUNTIFS('Test Cases'!$A:$A,$A8&"-*",'Test Cases'!$K:$K,"Pass") | E8: =COUNTIFS('Test Cases'!$A:$A,$A8&"-*",'Test Cases'!$K:$K,"Fail") | F8: =COUNTIFS('Test Cases'!$A:$A,$A8&"-*",'Test Cases'!$K:$K,"Blocked") | G8: =COUNTIFS('Test Cases'!$A:$A,$A8&"-*",'Test Cases'!$K:$K,"Chưa test") | H8: =IF(C8=0,0,D8/C8)
A9: PR | B9: Khuyến mãi / mã giảm giá | C9: =COUNTIF('Test Cases'!$A:$A,A9&"-*") | D9: =COUNTIFS('Test Cases'!$A:$A,$A9&"-*",'Test Cases'!$K:$K,"Pass") | E9: =COUNTIFS('Test Cases'!$A:$A,$A9&"-*",'Test Cases'!$K:$K,"Fail") | F9: =COUNTIFS('Test Cases'!$A:$A,$A9&"-*",'Test Cases'!$K:$K,"Blocked") | G9: =COUNTIFS('Test Cases'!$A:$A,$A9&"-*",'Test Cases'!$K:$K,"Chưa test") | H9: =IF(C9=0,0,D9/C9)
A10: CF | B10: Xác nhận đặt phòng | C10: =COUNTIF('Test Cases'!$A:$A,A10&"-*") | D10: =COUNTIFS('Test Cases'!$A:$A,$A10&"-*",'Test Cases'!$K:$K,"Pass") | E10: =COUNTIFS('Test Cases'!$A:$A,$A10&"-*",'Test Cases'!$K:$K,"Fail") | F10: =COUNTIFS('Test Cases'!$A:$A,$A10&"-*",'Test Cases'!$K:$K,"Blocked") | G10: =COUNTIFS('Test Cases'!$A:$A,$A10&"-*",'Test Cases'!$K:$K,"Chưa test") | H10: =IF(C10=0,0,D10/C10)
A11: PM | B11: Thanh toán (QR PayOS) | C11: =COUNTIF('Test Cases'!$A:$A,A11&"-*") | D11: =COUNTIFS('Test Cases'!$A:$A,$A11&"-*",'Test Cases'!$K:$K,"Pass") | E11: =COUNTIFS('Test Cases'!$A:$A,$A11&"-*",'Test Cases'!$K:$K,"Fail") | F11: =COUNTIFS('Test Cases'!$A:$A,$A11&"-*",'Test Cases'!$K:$K,"Blocked") | G11: =COUNTIFS('Test Cases'!$A:$A,$A11&"-*",'Test Cases'!$K:$K,"Chưa test") | H11: =IF(C11=0,0,D11/C11)
A12: IN | B12: Hỏi chen ngang / FAQ (RAG) | C12: =COUNTIF('Test Cases'!$A:$A,A12&"-*") | D12: =COUNTIFS('Test Cases'!$A:$A,$A12&"-*",'Test Cases'!$K:$K,"Pass") | E12: =COUNTIFS('Test Cases'!$A:$A,$A12&"-*",'Test Cases'!$K:$K,"Fail") | F12: =COUNTIFS('Test Cases'!$A:$A,$A12&"-*",'Test Cases'!$K:$K,"Blocked") | G12: =COUNTIFS('Test Cases'!$A:$A,$A12&"-*",'Test Cases'!$K:$K,"Chưa test") | H12: =IF(C12=0,0,D12/C12)
A13: LG | B13: Ngôn ngữ & định dạng input | C13: =COUNTIF('Test Cases'!$A:$A,A13&"-*") | D13: =COUNTIFS('Test Cases'!$A:$A,$A13&"-*",'Test Cases'!$K:$K,"Pass") | E13: =COUNTIFS('Test Cases'!$A:$A,$A13&"-*",'Test Cases'!$K:$K,"Fail") | F13: =COUNTIFS('Test Cases'!$A:$A,$A13&"-*",'Test Cases'!$K:$K,"Blocked") | G13: =COUNTIFS('Test Cases'!$A:$A,$A13&"-*",'Test Cases'!$K:$K,"Chưa test") | H13: =IF(C13=0,0,D13/C13)
... A19: AD | B19: Luồng Admin (Luồng C) | C19: =COUNTIF('Test Cases'!$A:$A,A19&"-*") | D19: =COUNTIFS('Test Cases'!$A:$A,$A19&"-*",'Test Cases'!$K:$K,"Pass") | E19: =COUNTIFS('Test Cases'!$A:$A,$A19&"-*",'Test Cases'!$K:$K,"Fail") | F19: =COUNTIFS('Test Cases'!$A:$A,$A19&"-*",'Test Cases'!$K:$K,"Blocked") | G19: =COUNTIFS('Test Cases'!$A:$A,$A19&"-*",'Test Cases'!$K:$K,"Chưa test") | H19: =IF(C19=0,0,D19/C19)
A20: TỔNG | C20: =SUM(C2:C19) | D20: =SUM(D2:D19) | E20: =SUM(E2:E19) | F20: =SUM(F2:F19) | G20: =SUM(G2:G19) | H20: =IF(C20=0,0,D20/C20)
A23: Ưu tiên | C23: Tổng | D23: Pass | E23: Fail | F23: Blocked | G23: Chưa test | H23: % Pass
A24: P0 | C24: =COUNTIF('Test Cases'!$C:$C,A24) | D24: =COUNTIFS('Test Cases'!$C:$C,$A24,'Test Cases'!$K:$K,"Pass") | E24: =COUNTIFS('Test Cases'!$C:$C,$A24,'Test Cases'!$K:$K,"Fail") | F24: =COUNTIFS('Test Cases'!$C:$C,$A24,'Test Cases'!$K:$K,"Blocked") | G24: =COUNTIFS('Test Cases'!$C:$C,$A24,'Test Cases'!$K:$K,"Chưa test") | H24: =IF(C24=0,0,D24/C24)
A25: P1 | C25: =COUNTIF('Test Cases'!$C:$C,A25) | D25: =COUNTIFS('Test Cases'!$C:$C,$A25,'Test Cases'!$K:$K,"Pass") | E25: =COUNTIFS('Test Cases'!$C:$C,$A25,'Test Cases'!$K:$K,"Fail") | F25: =COUNTIFS('Test Cases'!$C:$C,$A25,'Test Cases'!$K:$K,"Blocked") | G25: =COUNTIFS('Test Cases'!$C:$C,$A25,'Test Cases'!$K:$K,"Chưa test") | H25: =IF(C25=0,0,D25/C25)
A26: P2 | C26: =COUNTIF('Test Cases'!$C:$C,A26) | D26: =COUNTIFS('Test Cases'!$C:$C,$A26,'Test Cases'!$K:$K,"Pass") | E26: =COUNTIFS('Test Cases'!$C:$C,$A26,'Test Cases'!$K:$K,"Fail") | F26: =COUNTIFS('Test Cases'!$C:$C,$A26,'Test Cases'!$K:$K,"Blocked") | G26: =COUNTIFS('Test Cases'!$C:$C,$A26,'Test Cases'!$K:$K,"Chưa test") | H26: =IF(C26=0,0,D26/C26)
